Workbook

Sheet COVER PAGE
A1: Field_1 | B1: Field_2 | C1: Field_3 | D1: Field_4 | E1: Field_5 | F1: Field_6 | G1: Field_7 | H1: Field_8
D3: OmniBSIC Bank Ghana Limited
B7: BANK AND NOSTRO RECONCILIATION REPORT
B11: 20-Nov-25

Sheet BOG GHS
A1: Field_1 | B1: Field_2 | C1: Field_3 | D1: Field_4 | E1: Field_5 | F1: Field_6 | G1: Field_7 | H1: Field_8 | I1: Field_9 | J1: Field_10
B4: DEPT | D4: OPERATIONS | E4: BANK ACCOUNT NUMBER | F4: 0120730044000/0120730031000
B6: BRANCH | D6: HEAD OFFICE | E6: GENERAL LEDGER NAME | F6: BOG GHS
B8: REPORTING DATE | D8: 20-Nov-25 | E8: GENERAL LEDGER NUMBER | F8: 0010000090013
B10: REPORTING UNIT | D10: RECONCILIATION
C13: 20-Nov-2025 | D13: BALANCE PER BANK STATEMENT | E13: 2.7180713e+09 | I13: CR
B15: SN | C15: DATE | D15: DESCRIPTION | E15: AMOUNT | F15: GL Ref No. | G15: AGING(DAYS) | H15: RECON
D17: ADD: DEBIT IN OUR BOOKS BUT NOT CREDITED BY BOG
B18: 1 | C18: 17-Nov-2025 | D18: 355 DAY REPO - ACCES BANK( SECONDARY MARKET) MM CONTRACT LIQUIDATION | E18: 8777458.4 | F18: 000MTTB243320001 | G18: 3 | H18: INT DR
B19: 2 | C19: 17-Nov-2025 | D19: 355 DAY REPO - ACCES BANK( SECONDARY MARKET) MM CONTRACT LIQUIDATION | E19: 29999942 | F19: 000MTTB243320001 | G19: 3 | H19: INT DR
B20: 3 | C20: 17-Nov-2025 | D20: 353 DAY GOG BILL PURCHASE - BANK MM CONTRACT LIQUIDATION | E20: 8757105.4 | F20: 000MTTB243340001 | G20: 3 | H20: INT DR
B21: 4 | C21: 17-Nov-2025 | D21: 353 DAY GOG BILL PURCHASE - BANK MM CONTRACT LIQUIDATION | E21: 29999895 | F21: 000MTTB243340001 | G21: 3 | H21: INT DR
B22: 5 | C22: 17-Nov-2025 | D22: 350 DAY GOG BILL - BANK MM CONTRACT LIQUIDATION | E22: 14471096 | F22: 000MTTB243370001 | G22: 3 | H22: INT DR
B23: 6 | C23: 17-Nov-2025 | D23: 350 DAY GOG BILL - BANK MM CONTRACT LIQUIDATION | E23: 49999904 | F23: 000MTTB243370001 | G23: 3 | H23: INT DR
B24: 7 | C24: 17-Nov-2025 | D24: 336 SECONDARY MK - ACCESS MM CONTRACT LIQUIDATION | E24: 42226577 | F24: 000MTTB243510003 | G24: 3 | H24: INT DR
B25: 8 | C25: 17-Nov-2025 | D25: 336 SECONDARY MK - ACCESS MM CONTRACT LIQUIDATION | E25: 1.49985e+08 | F25: 000MTTB243510003 | G25: 3 | H25: INT DR
B26: 9 | C26: 19-Nov-2025 | D26: COMMISSION ON TREASURY BILL DD 17.11.2025 | E26: 151661.14 | F26: 000TBIL253230001 | G26: 1 | H26: INT DR
D28: TOTAL: | E28: =SUM($E$18:$E$27) -> 3.3436864e+08
D31: ADD: DEBIT ORIGINATED BY BOG BUT NOT CREDITED IN OUR BOOKS
B32: 1 | C32: 17-Nov-2025 | D32: SCCT TROPSAUC171125AS GTBIGHAC OMNIBSIC BANK GHANA /201/119943/1/1/0 | E32: 62474150 | F32: TROPSAUC171125AS | G32: 3 | H32: EXT DR
B33: 2 | C33: 18-Nov-2025 | D33: 52 20251118 CSDT 20251118S0035084 ABNGGHAC //OPERATIONCODE //DeliveryVersusPayment | E33: 679018.92 | F33: 20251118S0035084 | G33: 2 | H33: EXT DR
B34: 3 | C34: 18-Nov-2025 | D34: 80 20251118 NSI MCI1181125 | E34: 175565.37 | F34: MCI1181125 | G34: 2 | H34: EXT DR
B35: 4 | C35: 19-Nov-2025 | D35: 90 20251119 NSI MCI1191125 | E35: 80115.52 | F35: MCI1191125 | G35: 1 | H35: EXT DR
B36: 5 | C36: 20-Nov-2025 | D36: 7 20251120 CSDT 20251120S0000254 SSNTGHAC //OPERATIONCODE //ReverseRepoCollateral | E36: 7120821.9 | F36: 20251120S0000254 | G36: 0 | H36: EXT DR
B37: 6 | C37: 20-Nov-2025 | D37: 19 20251120 CSDT 20251120S0002183 HFCAGHAC //OPERATIONCODE //DeliveryVersusPayment | E37: 3639615.3 | F37: 20251120S0002183 | G37: 0 | H37: EXT DR
B38: 7 | C38: 20-Nov-2025 | D38: 20 20251120 CSDT 20251120S0002184 HFCAGHAC //OPERATIONCODE //DeliveryVersusPayment | E38: 1455846.5 | F38: 20251120S0002184 | G38: 0 | H38: EXT DR
B39: 8 | C39: 20-Nov-2025 | D39: 28 20251120 CSDT 20251120S0003292 ECOCGHAC //OPERATIONCODE //DeliveryVersusPayment | E39: 935901.32 | F39: 20251120S0003292 | G39: 0 | H39: EXT DR
B40: 9 | C40: 20-Nov-2025 | D40: 45 20251120 NSI 20251120T0016320 /// | E40: 7488523.9 | F40: 20251120T0016320 | G40: 0 | H40: EXT DR
B41: 10 | C41: 20-Nov-2025 | D41: 81 20251120 NSI 20251120T0022076 /// | E41: 1503001.7 | F41: 20251120T0022076 | G41: 0 | H41: EXT DR
B42: 11 | C42: 20-Nov-2025 | D42: 82 20251120 NSI GG07181125 | E42: 3814249.1 | F42: GG07181125 | G42: 0 | H42: EXT DR
B43: 12 | C43: 20-Nov-2025 | D43: 83 20251120 NSI GG08181125 | E43: 1401529.7 | F43: GG08181125 | G43: 0 | H43: EXT DR
... B46: 15 | C46: 20-Nov-2025 | D46: FIT TRSF01201125FAAM FAMCGHAC ISSN 76035 MATURITY SETTLEMENT FAMCCUS- | E46: 1127638 | F46: TRSF01201125FAAM | G46: 0 | H46: EXT DR
D48: TOTAL: | E48: =SUM($E$32:$E$47) -> 1.2538639e+08
D51: LESS: CREDIT ORIGINATED BY BOG BUT NOT DEBITED IN OUR BOOKS
B52: 1 | C52: 17-Nov-2025 | D52: 37 20251117 NSI 20251117T0009403 /ISIN/GHGGOG076035 | E52: 333538868 | F52: 20251117T0009403 | G52: 3 | H52: EXT CR
B53: 2 | C53: 20-Nov-2025 | D53: 63 20251120 NSI RGIP181125 | E53: 3988 | F53: RGIP181125 | G53: 0 | H53: EXT CR
B54: 3 | C54: 20-Nov-2025 | D54: 64 20251120 NSI RGIP201125 /6010194725 | E54: 194997 | F54: RGIP201125 | G54: 0 | H54: EXT CR
B55: 4 | C55: 20-Nov-2025 | D55: 86 20251120 NSI VISA201125 | E55: 33403.32 | F55: VISA201125 | G55: 0 | H55: EXT CR
D57: TOTAL: | E57: =SUM($E$52:$E$56) -> 3.3377126e+08
D60: LESS: CREDIT IN OUR BOOKS BUT NOT DEBITED BY BOG
B61: 1 | C61: 19-Nov-2025 | D61: SITTING ALLOWANCE FOR THE AUDIT BOARD SUB-COMMITTEE MEETING DD 18/NOV/2025 B/O OMNIBSIC BANK | E61: 6525 | F61: 000018x253230001 | G61: 1 | H61: INT CR
B62: 2 | C62: 19-Nov-2025 | D62: 91 DY REPO - SEM CAPITAL MM CONTRACT LIQUIDATION | E62: 231361.88 | F62: 000MM2L252320003 | G62: 1 | H62: INT CR
B63: 3 | C63: 19-Nov-2025 | D63: 91 DY REPO - SEM CAPITAL MM CONTRACT LIQUIDATION | E63: 5800001.2 | F63: 000MM2L252320003 | G63: 1 | H63: INT CR
B64: 4 | C64: 19-Nov-2025 | D64: TOTAL TREASURY BILL PURCHASE DD 18.11.2025 | E64: 62033066 | F64: 000TBIL253230001 | G64: 1 | H64: INT CR
B65: 5 | C65: 19-Nov-2025 | D65: FX PURCHASE - USD/GHS @ 11.10 (UNIV OF GH.) | E65: 2220000 | F65: 2532301465187000 | G65: 1 | H65: INT CR
B66: 6 | C66: 20-Nov-2025 | D66: PYMT FOR GARDENING & MAINTENANCE OF PLANTS AT HEADOFFICE AND CLASSIC BANKING LOUNGE FOR THE MONTH OF OCTOBER 2025 IFO THE GREEN LANDSCAPE B/O OMNIBSIC BANK | E66: 2035 | F66: 00000yv253240001 | G66: 0 | H66: INT CR
B67: 7 | C67: 20-Nov-2025 | D67: 91 DAY REPO - ALGEBRA MM CONTRACT LIQUIDATION | E67: 97332.02 | F67: 000MM2L252520002 | G67: 0 | H67: INT CR
B68: 8 | C68: 20-Nov-2025 | D68: 91 DAY REPO - ALGEBRA MM CONTRACT LIQUIDATION | E68: 2440000.1 | F68: 000MM2L252520002 | G68: 0 | H68: INT CR
B69: 9 | C69: 20-Nov-2025 | D69: 56 DAY REPO - BLACKSTAR MM CONTRACT LIQUIDATION | E69: 215179.28 | F69: 000MM2L252680006 | G69: 0 | H69: INT CR
B70: 10 | C70: 20-Nov-2025 | D70: 56 DAY REPO - BLACKSTAR MM CONTRACT LIQUIDATION | E70: 8299169.4 | F70: 000MM2L252680006 | G70: 0 | H70: INT CR
B71: 11 | C71: 20-Nov-2025 | D71: 56 DAY REPO SIC FSL 2 MM CONTRACT LIQUIDATION | E71: 10933.06 | F71: 000MM2L252680503 | G71: 0 | H71: INT CR
B72: 12 | C72: 20-Nov-2025 | D72: 56 DAY REPO SIC FSL 2 MM CONTRACT LIQUIDATION | E72: 466243.94 | F72: 000MM2L252680503 | G72: 0 | H72: INT CR
B73: 13 | C73: 20-Nov-2025 | D73: 56 DAY REPO - CONSTANT CAPITAL MM CONTRACT LIQUIDATION DD 250925 | E73: 1733907.3 | F73: TS11201125001 | G73: 0 | H73: INT CR
D75: TOTAL: | E75: =SUM($E$61:$E$74) -> 83555754
D78: GRAND TOTAL | E78: =ABS(E13+$E$28-$E$75+$E$48-$E$57) -> 2.7604994e+09
D79: INTERNAL ACCOUNT BALANCE AS AT Nov 20, 2025 | E79: 2.7604994e+09 | I79: DR
D80: DIFFERENCE | E80: =$E$79-$E$78 -> 0
D82: PREPARED BY: | E82: kenneth nuamah | F82: DATE: | G82: 45981
D85: REVIEWED BY: | F85: DATE:

Sheet BOG USD
A1: Field_1 | B1: Field_2 | C1: Field_3 | D1: Field_4 | E1: Field_5 | F1: Field_6 | G1: Field_7 | H1: Field_8 | I1: Field_9 | J1: Field_10
B4: DEPT | D4: OPERATIONS | E4: BANK ACCOUNT NUMBER | F4: 1027232397011
B6: BRANCH | D6: HEAD OFFICE | E6: GENERAL LEDGER NAME | F6: BOG USD
B8: REPORTING DATE | D8: 20-Nov-25 | E8: GENERAL LEDGER NUMBER | F8: 0020000090010
B10: REPORTING UNIT | D10: RECONCILIATION
C13: 20-Nov-2025 | D13: BALANCE PER BANK STATEMENT | E13: 44709005 | I13: CR
B15: SN | C15: DATE | D15: DESCRIPTION | E15: AMOUNT | F15: GL Ref No. | G15: AGING(DAYS) | H15: RECON
D17: ADD: DEBIT IN OUR BOOKS BUT NOT CREDITED BY BOG
B18: 1 | C18: 12-Nov-2025 | D18: 0000189253160001_FINCON JOURNAL ENTRY | E18: 4400 | G18: 8 | H18: INT DR
B19: 2 | C19: 19-Nov-2025 | D19: FX PURCHASE - USD/GHS @ 11.10 (UNIV OF GH.) | E19: 200000 | F19: 2532301465187000 | G19: 1 | H19: INT DR
B20: 3 | C20: 20-Nov-2025 | D20: FX SALE - USD/GHS @ 11.10 (USD 140,000.00 MASTERCARD) | E20: 140000 | F20: 2532401461518000 | G20: 0 | H20: INT DR
B21: 4 | C21: 20-Nov-2025 | D21: FX SALE - USD/GHS @ 11.10 (USD 20,000.00 MASTERCARD) | E21: 20000 | F21: 2532401461593000 | G21: 0 | H21: INT DR
B22: 5 | C22: 20-Nov-2025 | D22: FX SALE - USD/GHS @ 11.10 (USD 100,000.00 MASTERCARD) | E22: 100000 | F22: 2532401461658000 | G22: 0 | H22: INT DR
D24: TOTAL: | E24: =SUM($E$18:$E$23) -> 464400
D27: ADD: DEBIT ORIGINATED BY BOG BUT NOT CREDITED IN OUR BOOKS
D30: TOTAL: | E30: =SUM($E$28:$E$29) -> 0
D33: LESS: CREDIT ORIGINATED BY BOG BUT NOT DEBITED IN OUR BOOKS
B34: 1 | C34: 03-Nov-2025 | D34: FNB253070KGFFJHL FIRNGHAC /2021015043307 GHANA SPECIALTY FATS INDUSTRIES LTD /0020039684014 AMARIS TERMINAL LIMITED WAREHOUSE RENTAL | E34: 15000 | G34: 17 | H34: EXT CR
B35: 2 | C35: 19-Nov-2025 | D35: 1 20251119 SCCT GTBFTDC251130741 GTBIGHAC /1027232397011 BENJAMIN CARGO LOGISTICS | E35: 600 | F35: GTBFTDC251130741 | G35: 1 | H35: EXT CR
B36: 3 | C36: 20-Nov-2025 | D36: 2 20251120 SCCT GH06432425HLE85 BARCGHAC /0020233906018 PAA YOOKU YAWSON | E36: 6000 | F36: GH06432425HLE85 | G36: 0 | H36: EXT CR
D38: TOTAL: | E38: =SUM($E$34:$E$37) -> 21600
D41: LESS: CREDIT IN OUR BOOKS BUT NOT DEBITED BY BOG
B42: 1 | C42: 13-Oct-2025 | D42: OMNCHQ20250995 PYT OF CHQ#009463 IFO ETHOS RISK PROTECTION PARTNERS | E42: 67.02 | G42: 38 | H42: INT CR
B43: 2 | C43: 13-Nov-2025 | D43: OMNCHQ20251031 PYT OF CHQ#000106 IFO KHADIJA ADAM | E43: 345.73 | F43: OMNCHQ20251031 | G43: 7 | H43: INT CR
D45: TOTAL: | E45: =SUM($E$42:$E$44) -> 412.75
D48: GRAND TOTAL | E48: =ABS(E13+$E$24-$E$45+$E$30-$E$38) -> 45151392
D49: INTERNAL ACCOUNT BALANCE AS AT Nov 20, 2025 | E49: 45151392 | I49: DR
D50: DIFFERENCE | E50: =$E$49-$E$48 -> 0
D52: PREPARED BY: | E52: kenneth nuamah | F52: DATE: | G52: 45981
D55: REVIEWED BY: | F55: DATE:

Sheet BOG EUR
A1: Field_1 | B1: Field_2 | C1: Field_3 | D1: Field_4 | E1: Field_5 | F1: Field_6 | G1: Field_7 | H1: Field_8 | I1: Field_9 | J1: Field_10
B4: DEPT | D4: OPERATIONS | E4: BANK ACCOUNT NUMBER | F4: ^1187232397019
B6: BRANCH | D6: HEAD OFFICE | E6: GENERAL LEDGER NAME | F6: BOG EUR
B8: REPORTING DATE | D8: 20-Nov-25 | E8: GENERAL LEDGER NUMBER | F8: 0030000090018
B10: REPORTING UNIT | D10: RECONCILIATION
C13: 20-Nov-2025 | D13: BALANCE PER BANK STATEMENT | E13: 1063124.2 | I13: CR
B15: SN | C15: DATE | D15: DESCRIPTION | E15: AMOUNT | F15: GL Ref No. | G15: AGING(DAYS) | H15: RECON
D17: ADD: DEBIT IN OUR BOOKS BUT NOT CREDITED BY BOG
D20: TOTAL: | E20: =SUM($E$18:$E$19) -> 0
D23: ADD: DEBIT ORIGINATED BY BOG BUT NOT CREDITED IN OUR BOOKS
D26: TOTAL: | E26: =SUM($E$24:$E$25) -> 0
D29: LESS: CREDIT ORIGINATED BY BOG BUT NOT DEBITED IN OUR BOOKS
D32: TOTAL: | E32: =SUM($E$30:$E$31) -> 0
D35: LESS: CREDIT IN OUR BOOKS BUT NOT DEBITED BY BOG
D38: TOTAL: | E38: =SUM($E$36:$E$37) -> 0
D41: GRAND TOTAL | E41: =ABS(E13+$E$20-$E$38+$E$26-$E$32) -> 1063124.2
D42: INTERNAL ACCOUNT BALANCE AS AT Nov 20, 2025 | E42: 1063124.2 | I42: DR
D43: DIFFERENCE | E43: =$E$42-$E$41 -> 0
D45: PREPARED BY: | E45: kenneth nuamah | F45: DATE: | G45: 45981
D48: REVIEWED BY: | F48: DATE:

Sheet BOG GBP
A1: Field_1 | B1: Field_2 | C1: Field_3 | D1: Field_4 | E1: Field_5 | F1: Field_6 | G1: Field_7 | H1: Field_8 | I1: Field_9 | J1: Field_10
B4: DEPT | D4: OPERATIONS | E4: BANK ACCOUNT NUMBER | F4: ^1037232397017
B6: BRANCH | D6: HEAD OFFICE | E6: GENERAL LEDGER NAME | F6: BOG GBP
B8: REPORTING DATE | D8: 20-Nov-25 | E8: GENERAL LEDGER NUMBER | F8: 0040000090015
B10: REPORTING UNIT | D10: RECONCILIATION
C13: 20-Nov-2025 | D13: BALANCE PER BANK STATEMENT | E13: 703521.11 | I13: CR
B15: SN | C15: DATE | D15: DESCRIPTION | E15: AMOUNT | F15: GL Ref No. | G15: AGING(DAYS) | H15: RECON
D17: ADD: DEBIT IN OUR BOOKS BUT NOT CREDITED BY BOG
D20: TOTAL: | E20: =SUM($E$18:$E$19) -> 0
D23: ADD: DEBIT ORIGINATED BY BOG BUT NOT CREDITED IN OUR BOOKS
D26: TOTAL: | E26: =SUM($E$24:$E$25) -> 0
D29: LESS: CREDIT ORIGINATED BY BOG BUT NOT DEBITED IN OUR BOOKS
D32: TOTAL: | E32: =SUM($E$30:$E$31) -> 0
D35: LESS: CREDIT IN OUR BOOKS BUT NOT DEBITED BY BOG
D38: TOTAL: | E38: =SUM($E$36:$E$37) -> 0
D41: GRAND TOTAL | E41: =ABS(E13+$E$20-$E$38+$E$26-$E$32) -> 703521.11
D42: INTERNAL ACCOUNT BALANCE AS AT Nov 20, 2025 | E42: 703521.11 | I42: DR
D43: DIFFERENCE | E43: =$E$42-$E$41 -> 0
D45: PREPARED BY: | E45: kenneth nuamah | F45: DATE: | G45: 45981
D48: REVIEWED BY: | F48: DATE:

Sheet BOG PAPSS GHS
A1: Field_1 | B1: Field_2 | C1: Field_3 | D1: Field_4 | E1: Field_5 | F1: Field_6 | G1: Field_7 | H1: Field_8 | I1: Field_9 | J1: Field_10
B4: DEPT | D4: OPERATIONS | E4: BANK ACCOUNT NUMBER | F4: GH100017
B6: BRANCH | D6: HEAD OFFICE | E6: GENERAL LEDGER NAME | F6: BOG -ACCRA- PAPSS
B8: REPORTING DATE | D8: 20-Nov-25 | E8: GENERAL LEDGER NUMBER | F8: 0010000090024
B10: REPORTING UNIT | D10: RECONCILIATION
C13: 20-Nov-2025 | D13: BALANCE PER BANK STATEMENT | E13: 103818.35 | I13: CR
B15: SN | C15: DATE | D15: DESCRIPTION | E15: AMOUNT | F15: GL Ref No. | G15: AGING(DAYS) | H15: RECON
D17: ADD: DEBIT IN OUR BOOKS BUT NOT CREDITED BY BOG
B18: 1 | C18: 07-Nov-2025 | D18: Allowance to mother | E18: 719.14 | F18: 7679014267440990 | G18: 13 | H18: INT DR
D20: TOTAL: | E20: =SUM($E$18:$E$19) -> 719.14
D23: ADD: DEBIT ORIGINATED BY BOG BUT NOT CREDITED IN OUR BOOKS
D26: TOTAL: | E26: =SUM($E$24:$E$25) -> 0
D29: LESS: CREDIT ORIGINATED BY BOG BUT NOT DEBITED IN OUR BOOKS
D32: TOTAL: | E32: =SUM($E$30:$E$31) -> 0
D35: LESS: CREDIT IN OUR BOOKS BUT NOT DEBITED BY BOG
D38: TOTAL: | E38: =SUM($E$36:$E$37) -> 0
D41: GRAND TOTAL | E41: =ABS(E13+$E$20-$E$38+$E$26-$E$32) -> 104537.49
D42: INTERNAL ACCOUNT BALANCE AS AT Nov 20, 2025 | E42: 104537.49 | I42: DR
D43: DIFFERENCE | E43: =$E$42-$E$41 -> 0
D45: PREPARED BY: | E45: Ebenezer Frimpong | F45: DATE: | G45: 45981
D48: REVIEWED BY: | F48: DATE:

Sheet BOG KSI GHS
A1: Field_1 | B1: Field_2 | C1: Field_3 | D1: Field_4 | E1: Field_5 | F1: Field_6 | G1: Field_7 | H1: Field_8 | I1: Field_9 | J1: Field_10
B4: DEPT | D4: OPERATIONS | E4: BANK ACCOUNT NUMBER | F4: 2017231344017
B6: BRANCH | D6: HEAD OFFICE | E6: GENERAL LEDGER NAME | F6: BANK OF GHANA -KUMASI-GHS
B8: REPORTING DATE | D8: 20-Nov-25 | E8: GENERAL LEDGER NUMBER | F8: 0010113040010
B10: REPORTING UNIT | D10: RECONCILIATION
C13: 20-Nov-2025 | D13: BALANCE PER BANK STATEMENT | E13: 7025754.9 | I13: CR
B15: SN | C15: DATE | D15: DESCRIPTION | E15: AMOUNT | F15: GL Ref No. | G15: AGING(DAYS) | H15: RECON
D17: ADD: DEBIT IN OUR BOOKS BUT NOT CREDITED BY BOG
D20: TOTAL: | E20: =SUM($E$18:$E$19) -> 0
D23: ADD: DEBIT ORIGINATED BY BOG BUT NOT CREDITED IN OUR BOOKS
D26: TOTAL: | E26: =SUM($E$24:$E$25) -> 0
D29: LESS: CREDIT ORIGINATED BY BOG BUT NOT DEBITED IN OUR BOOKS
D32: TOTAL: | E32: =SUM($E$30:$E$31) -> 0
D35: LESS: CREDIT IN OUR BOOKS BUT NOT DEBITED BY BOG
D38: TOTAL: | E38: =SUM($E$36:$E$37) -> 0
D41: GRAND TOTAL | E41: =ABS(E13+$E$20-$E$38+$E$26-$E$32) -> 7025754.9
D42: INTERNAL ACCOUNT BALANCE AS AT Nov 20, 2025 | E42: 7025754.9 | I42: DR
D43: DIFFERENCE | E43: =$E$42-$E$41 -> 0
D45: PREPARED BY: | E45: kenneth nuamah | F45: DATE: | G45: 45981
D48: REVIEWED BY: | F48: DATE:

Sheet BOG KSI USD
A1: Field_1 | B1: Field_2 | C1: Field_3 | D1: Field_4 | E1: Field_5 | F1: Field_6 | G1: Field_7 | H1: Field_8 | I1: Field_9 | J1: Field_10
B4: DEPT | D4: OPERATIONS | E4: BANK ACCOUNT NUMBER | F4: 2027231344015
B6: BRANCH | D6: HEAD OFFICE | E6: GENERAL LEDGER NAME | F6: BANK OF GHANA -KUMASI-USD
B8: REPORTING DATE | D8: 20-Nov-25 | E8: GENERAL LEDGER NUMBER | F8: 0020113040018
B10: REPORTING UNIT | D10: RECONCILIATION
C13: 2025-10-31 | D13: BALANCE PER BANK STATEMENT | E13: 1103000 | I13: CR
B15: SN | C15: DATE | D15: DESCRIPTION | E15: AMOUNT | F15: GL Ref No. | G15: AGING(DAYS) | H15: RECON
D17: ADD: DEBIT IN OUR BOOKS BUT NOT CREDITED BY BOG
D20: TOTAL: | E20: =SUM($E$18:$E$19) -> 0
D23: ADD: DEBIT ORIGINATED BY BOG BUT NOT CREDITED IN OUR BOOKS
D26: TOTAL: | E26: =SUM($E$24:$E$25) -> 0
D29: LESS: CREDIT ORIGINATED BY BOG BUT NOT DEBITED IN OUR BOOKS
D32: TOTAL: | E32: =SUM($E$30:$E$31) -> 0
D35: LESS: CREDIT IN OUR BOOKS BUT NOT DEBITED BY BOG
D38: TOTAL: | E38: =SUM($E$36:$E$37) -> 0
D41: GRAND TOTAL | E41: =ABS(E13+$E$20-$E$38+$E$26-$E$32) -> 1103000
D42: INTERNAL ACCOUNT BALANCE AS AT Nov 20, 2025 | E42: 1103000 | I42: DR
D43: DIFFERENCE | E43: =$E$42-$E$41 -> 0
D45: PREPARED BY: | E45: kenneth nuamah | F45: DATE: | G45: 45981
D48: REVIEWED BY: | F48: DATE:

Sheet BOG KSI EUR
A1: Field_1 | B1: Field_2 | C1: Field_3 | D1: Field_4 | E1: Field_5 | F1: Field_6 | G1: Field_7 | H1: Field_8 | I1: Field_9 | J1: Field_10
B4: DEPT | D4: OPERATIONS | E4: BANK ACCOUNT NUMBER | F4: 2187231344012
B6: BRANCH | D6: HEAD OFFICE | E6: GENERAL LEDGER NAME | F6: BANK OF GHANA -KUMASI-EUR
B8: REPORTING DATE | D8: 20-Nov-25 | E8: GENERAL LEDGER NUMBER | F8: 0030113040015
B10: REPORTING UNIT | D10: RECONCILIATION
C13: 2025-10-31 | D13: BALANCE PER BANK STATEMENT | E13: 260500 | I13: CR
B15: SN | C15: DATE | D15: DESCRIPTION | E15: AMOUNT | F15: GL Ref No. | G15: AGING(DAYS) | H15: RECON
D17: ADD: DEBIT IN OUR BOOKS BUT NOT CREDITED BY BOG
D20: TOTAL: | E20: =SUM($E$18:$E$19) -> 0
D23: ADD: DEBIT ORIGINATED BY BOG BUT NOT CREDITED IN OUR BOOKS
D26: TOTAL: | E26: =SUM($E$24:$E$25) -> 0
D29: LESS: CREDIT ORIGINATED BY BOG BUT NOT DEBITED IN OUR BOOKS
D32: TOTAL: | E32: =SUM($E$30:$E$31) -> 0
D35: LESS: CREDIT IN OUR BOOKS BUT NOT DEBITED BY BOG
D38: TOTAL: | E38: =SUM($E$36:$E$37) -> 0
D41: GRAND TOTAL | E41: =ABS(E13+$E$20-$E$38+$E$26-$E$32) -> 260500
D42: INTERNAL ACCOUNT BALANCE AS AT Nov 20, 2025 | E42: 260500 | I42: DR
D43: DIFFERENCE | E43: =$E$42-$E$41 -> 0
D45: PREPARED BY: | E45: kenneth nuamah | F45: DATE: | G45: 45981
D48: REVIEWED BY: | F48: DATE:

Sheet BOG KSI GBP
A1: Field_1 | B1: Field_2 | C1: Field_3 | D1: Field_4 | E1: Field_5 | F1: Field_6 | G1: Field_7 | H1: Field_8 | I1: Field_9 | J1: Field_10
B4: DEPT | D4: OPERATIONS | E4: BANK ACCOUNT NUMBER | F4: 2037231344018
B6: BRANCH | D6: HEAD OFFICE | E6: GENERAL LEDGER NAME | F6: BANK OF GHANA -KUMASI-GBP
B8: REPORTING DATE | D8: 20-Nov-25 | E8: GENERAL LEDGER NUMBER | F8: 0040113040012
B10: REPORTING UNIT | D10: RECONCILIATION
C13: 2025-10-31 | D13: BALANCE PER BANK STATEMENT | E13: 48843.2 | I13: CR
B15: SN | C15: DATE | D15: DESCRIPTION | E15: AMOUNT | F15: GL Ref No. | G15: AGING(DAYS) | H15: RECON
D17: ADD: DEBIT IN OUR BOOKS BUT NOT CREDITED BY BOG
D20: TOTAL: | E20: =SUM($E$18:$E$19) -> 0
D23: ADD: DEBIT ORIGINATED BY BOG BUT NOT CREDITED IN OUR BOOKS
D26: TOTAL: | E26: =SUM($E$24:$E$25) -> 0
D29: LESS: CREDIT ORIGINATED BY BOG BUT NOT DEBITED IN OUR BOOKS
D32: TOTAL: | E32: =SUM($E$30:$E$31) -> 0
D35: LESS: CREDIT IN OUR BOOKS BUT NOT DEBITED BY BOG
D38: TOTAL: | E38: =SUM($E$36:$E$37) -> 0
D41: GRAND TOTAL | E41: =ABS(E13+$E$20-$E$38+$E$26-$E$32) -> 48843.2
D42: INTERNAL ACCOUNT BALANCE AS AT Nov 20, 2025 | E42: 48843.2 | I42: DR
D43: DIFFERENCE | E43: =$E$42-$E$41 -> 0
D45: PREPARED BY: | E45: kenneth nuamah | F45: DATE: | G45: 45981
D48: REVIEWED BY: | F48: DATE:

Sheet BOG SYI GHS
A1: Field_1 | B1: Field_2 | C1: Field_3 | D1: Field_4 | E1: Field_5 | F1: Field_6 | G1: Field_7 | H1: Field_8 | I1: Field_9 | J1: Field_10
B4: DEPT | D4: OPERATIONS | E4: BANK ACCOUNT NUMBER | F4: 4017131344017
B6: BRANCH | D6: HEAD OFFICE | E6: GENERAL LEDGER NAME | F6: BANK OF GHANA -SUNYANI-GHS
B8: REPORTING DATE | D8: 20-Nov-25 | E8: GENERAL LEDGER NUMBER | F8: 0010086657018
B10: REPORTING UNIT | D10: RECONCILIATION
C13: 19-Nov-2025 | D13: BALANCE PER BANK STATEMENT | E13: 46082773 | I13: CR
B15: SN | C15: DATE | D15: DESCRIPTION | E15: AMOUNT | F15: GL Ref No. | G15: AGING(DAYS) | H15: RECON
D17: ADD: DEBIT IN OUR BOOKS BUT NOT CREDITED BY BOG
D20: TOTAL: | E20: =SUM($E$18:$E$19) -> 0
D23: ADD: DEBIT ORIGINATED BY BOG BUT NOT CREDITED IN OUR BOOKS
D26: TOTAL: | E26: =SUM($E$24:$E$25) -> 0
D29: LESS: CREDIT ORIGINATED BY BOG BUT NOT DEBITED IN OUR BOOKS
D32: TOTAL: | E32: =SUM($E$30:$E$31) -> 0
D35: LESS: CREDIT IN OUR BOOKS BUT NOT DEBITED BY BOG
D38: TOTAL: | E38: =SUM($E$36:$E$37) -> 0
D41: GRAND TOTAL | E41: =ABS(E13+$E$20-$E$38+$E$26-$E$32) -> 46082773
D42: INTERNAL ACCOUNT BALANCE AS AT Nov 20, 2025 | E42: 46082773 | I42: DR
D43: DIFFERENCE | E43: =$E$42-$E$41 -> 0
D45: PREPARED BY: | E45: kenneth nuamah | F45: DATE: | G45: 45981
D48: REVIEWED BY: | F48: DATE:

Sheet BOG SYI USD
A1: Field_1 | B1: Field_2 | C1: Field_3 | D1: Field_4 | E1: Field_5 | F1: Field_6 | G1: Field_7 | H1: Field_8 | I1: Field_9 | J1: Field_10
B4: DEPT | D4: OPERATIONS | E4: BANK ACCOUNT NUMBER | F4: 4027231344012
B6: BRANCH | D6: HEAD OFFICE | E6: GENERAL LEDGER NAME | F6: BANK OF GHANA -SUNYANI-USD
B8: REPORTING DATE | D8: 20-Nov-25 | E8: GENERAL LEDGER NUMBER | F8: 0020086657015
B10: REPORTING UNIT | D10: RECONCILIATION
C13: 2025-10-31 | D13: BALANCE PER BANK STATEMENT | E13: 30000 | I13: CR
B15: SN | C15: DATE | D15: DESCRIPTION | E15: AMOUNT | F15: GL Ref No. | G15: AGING(DAYS) | H15: RECON
D17: ADD: DEBIT IN OUR BOOKS BUT NOT CREDITED BY BOG
D20: TOTAL: | E20: =SUM($E$18:$E$19) -> 0
D23: ADD: DEBIT ORIGINATED BY BOG BUT NOT CREDITED IN OUR BOOKS
D26: TOTAL: | E26: =SUM($E$24:$E$25) -> 0
D29: LESS: CREDIT ORIGINATED BY BOG BUT NOT DEBITED IN OUR BOOKS
D32: TOTAL: | E32: =SUM($E$30:$E$31) -> 0
D35: LESS: CREDIT IN OUR BOOKS BUT NOT DEBITED BY BOG
D38: TOTAL: | E38: =SUM($E$36:$E$37) -> 0
D41: GRAND TOTAL | E41: =ABS(E13+$E$20-$E$38+$E$26-$E$32) -> 30000
D42: INTERNAL ACCOUNT BALANCE AS AT Nov 20, 2025 | E42: 30000 | I42: DR
D43: DIFFERENCE | E43: =$E$42-$E$41 -> 0
D45: PREPARED BY: | E45: kenneth nuamah | F45: DATE: | G45: 45981
D48: REVIEWED BY: | F48: DATE:

Sheet BOG SYI EUR
A1: Field_1 | B1: Field_2 | C1: Field_3 | D1: Field_4 | E1: Field_5 | F1: Field_6 | G1: Field_7 | H1: Field_8 | I1: Field_9 | J1: Field_10
B4: DEPT | D4: OPERATIONS | E4: BANK ACCOUNT NUMBER | F4: 4027231344012
B6: BRANCH | D6: HEAD OFFICE | E6: GENERAL LEDGER NAME | F6: BANK OF GHANA -SUNYANI-EUR
B8: REPORTING DATE | D8: 20-Nov-25 | E8: GENERAL LEDGER NUMBER | F8: 0020086657015
B10: REPORTING UNIT | D10: RECONCILIATION
C13: 2025-10-31 | D13: BALANCE PER BANK STATEMENT | E13: 0 | I13: CR
B15: SN | C15: DATE | D15: DESCRIPTION | E15: AMOUNT | F15: GL Ref No. | G15: AGING(DAYS) | H15: RECON
D17: ADD: DEBIT IN OUR BOOKS BUT NOT CREDITED BY BOG
D20: TOTAL: | E20: =SUM($E$18:$E$19) -> 0
D23: ADD: DEBIT ORIGINATED BY BOG BUT NOT CREDITED IN OUR BOOKS
D26: TOTAL: | E26: =SUM($E$24:$E$25) -> 0
D29: LESS: CREDIT ORIGINATED BY BOG BUT NOT DEBITED IN OUR BOOKS
D32: TOTAL: | E32: =SUM($E$30:$E$31) -> 0
D35: LESS: CREDIT IN OUR BOOKS BUT NOT DEBITED BY BOG
D38: TOTAL: | E38: =SUM($E$36:$E$37) -> 0
D41: GRAND TOTAL | E41: =ABS(E13+$E$20-$E$38+$E$26-$E$32) -> 0
D42: INTERNAL ACCOUNT BALANCE AS AT Nov 20, 2025 | E42: 0 | I42: DR
D43: DIFFERENCE | E43: =$E$42-$E$41 -> 0
D45: PREPARED BY: | E45: kenneth nuamah | F45: DATE: | G45: 45981
D48: REVIEWED BY: | F48: DATE:

Sheet BOG SYI GBP
A1: Field_1 | B1: Field_2 | C1: Field_3 | D1: Field_4 | E1: Field_5 | F1: Field_6 | G1: Field_7 | H1: Field_8 | I1: Field_9 | J1: Field_10
B4: DEPT | D4: OPERATIONS | E4: BANK ACCOUNT NUMBER | F4: 4027231344012
B6: BRANCH | D6: HEAD OFFICE | E6: GENERAL LEDGER NAME | F6: BANK OF GHANA -SUNYANI-GBP
B8: REPORTING DATE | D8: 20-Nov-25 | E8: GENERAL LEDGER NUMBER | F8: 0020086657015
B10: REPORTING UNIT | D10: RECONCILIATION
C13: 2025-10-31 | D13: BALANCE PER BANK STATEMENT | E13: 0 | I13: CR
B15: SN | C15: DATE | D15: DESCRIPTION | E15: AMOUNT | F15: GL Ref No. | G15: AGING(DAYS) | H15: RECON
D17: ADD: DEBIT IN OUR BOOKS BUT NOT CREDITED BY BOG
D20: TOTAL: | E20: =SUM($E$18:$E$19) -> 0
D23: ADD: DEBIT ORIGINATED BY BOG BUT NOT CREDITED IN OUR BOOKS
D26: TOTAL: | E26: =SUM($E$24:$E$25) -> 0
D29: LESS: CREDIT ORIGINATED BY BOG BUT NOT DEBITED IN OUR BOOKS
D32: TOTAL: | E32: =SUM($E$30:$E$31) -> 0
D35: LESS: CREDIT IN OUR BOOKS BUT NOT DEBITED BY BOG
D38: TOTAL: | E38: =SUM($E$36:$E$37) -> 0
D41: GRAND TOTAL | E41: =ABS(E13+$E$20-$E$38+$E$26-$E$32) -> 0
D42: INTERNAL ACCOUNT BALANCE AS AT Nov 20, 2025 | E42: 0 | I42: DR
D43: DIFFERENCE | E43: =$E$42-$E$41 -> 0
D45: PREPARED BY: | E45: kenneth nuamah | F45: DATE: | G45: 45981
D48: REVIEWED BY: | F48: DATE:

Sheet BOG TDI GHS
A1: Field_1 | B1: Field_2 | C1: Field_3 | D1: Field_4 | E1: Field_5 | F1: Field_6 | G1: Field_7 | H1: Field_8 | I1: Field_9 | J1: Field_10
B4: DEPT | D4: OPERATIONS | E4: BANK ACCOUNT NUMBER | F4: 3017231344013
B6: BRANCH | D6: HEAD OFFICE | E6: GENERAL LEDGER NAME | F6: BANK OF GHANA -TAKORADI-GHS
B8: REPORTING DATE | D8: 20-Nov-25 | E8: GENERAL LEDGER NUMBER | F8: 0010113730019
B10: REPORTING UNIT | D10: RECONCILIATION
C13: 19-Nov-2025 | D13: BALANCE PER BANK STATEMENT | E13: 6801989 | I13: CR
B15: SN | C15: DATE | D15: DESCRIPTION | E15: AMOUNT | F15: GL Ref No. | G15: AGING(DAYS) | H15: RECON
D17: ADD: DEBIT IN OUR BOOKS BUT NOT CREDITED BY BOG
D20: TOTAL: | E20: =SUM($E$18:$E$19) -> 0
D23: ADD: DEBIT ORIGINATED BY BOG BUT NOT CREDITED IN OUR BOOKS
D26: TOTAL: | E26: =SUM($E$24:$E$25) -> 0
D29: LESS: CREDIT ORIGINATED BY BOG BUT NOT DEBITED IN OUR BOOKS
D32: TOTAL: | E32: =SUM($E$30:$E$31) -> 0
D35: LESS: CREDIT IN OUR BOOKS BUT NOT DEBITED BY BOG
D38: TOTAL: | E38: =SUM($E$36:$E$37) -> 0
D41: GRAND TOTAL | E41: =ABS(E13+$E$20-$E$38+$E$26-$E$32) -> 6801989
D42: INTERNAL ACCOUNT BALANCE AS AT Nov 20, 2025 | E42: 6801989 | I42: DR
D43: DIFFERENCE | E43: =$E$42-$E$41 -> 0
D45: PREPARED BY: | E45: kenneth nuamah | F45: DATE: | G45: 45981
D48: REVIEWED BY: | F48: DATE:

Sheet BOG TDI USD
A1: Field_1 | B1: Field_2 | C1: Field_3 | D1: Field_4 | E1: Field_5 | F1: Field_6 | G1: Field_7 | H1: Field_8 | I1: Field_9 | J1: Field_10
B4: DEPT | D4: OPERATIONS | E4: BANK ACCOUNT NUMBER | F4: 3027231344019
B6: BRANCH | D6: HEAD OFFICE | E6: GENERAL LEDGER NAME | F6: BANK OF GHANA -TAKORADI-USD
B8: REPORTING DATE | D8: 20-Nov-25 | E8: GENERAL LEDGER NUMBER | F8: 0020113730016
B10: REPORTING UNIT | D10: RECONCILIATION
C13: 2025-11-11 | D13: BALANCE PER BANK STATEMENT | E13: 72200 | I13: CR
B15: SN | C15: DATE | D15: DESCRIPTION | E15: AMOUNT | F15: GL Ref No. | G15: AGING(DAYS) | H15: RECON
D17: ADD: DEBIT IN OUR BOOKS BUT NOT CREDITED BY BOG
D20: TOTAL: | E20: =SUM($E$18:$E$19) -> 0
D23: ADD: DEBIT ORIGINATED BY BOG BUT NOT CREDITED IN OUR BOOKS
D26: TOTAL: | E26: =SUM($E$24:$E$25) -> 0
D29: LESS: CREDIT ORIGINATED BY BOG BUT NOT DEBITED IN OUR BOOKS
D32: TOTAL: | E32: =SUM($E$30:$E$31) -> 0
D35: LESS: CREDIT IN OUR BOOKS BUT NOT DEBITED BY BOG
D38: TOTAL: | E38: =SUM($E$36:$E$37) -> 0
D41: GRAND TOTAL | E41: =ABS(E13+$E$20-$E$38+$E$26-$E$32) -> 72200
D42: INTERNAL ACCOUNT BALANCE AS AT Nov 20, 2025 | E42: 72200 | I42: DR
D43: DIFFERENCE | E43: =$E$42-$E$41 -> 0
D45: PREPARED BY: | E45: kenneth nuamah | F45: DATE: | G45: 45981
D48: REVIEWED BY: | F48: DATE:

Sheet BOG TDI EUR
A1: Field_1 | B1: Field_2 | C1: Field_3 | D1: Field_4 | E1: Field_5 | F1: Field_6 | G1: Field_7 | H1: Field_8 | I1: Field_9 | J1: Field_10
B4: DEPT | D4: OPERATIONS | E4: BANK ACCOUNT NUMBER | F4: 3187231344016
B6: BRANCH | D6: HEAD OFFICE | E6: GENERAL LEDGER NAME | F6: BANK OF GHANA -TAKORADI- EUR
B8: REPORTING DATE | D8: 20-Nov-25 | E8: GENERAL LEDGER NUMBER | F8: 0030113730013
B10: REPORTING UNIT | D10: RECONCILIATION
C13: 2025-11-11 | D13: BALANCE PER BANK STATEMENT | E13: 159835 | I13: CR
B15: SN | C15: DATE | D15: DESCRIPTION | E15: AMOUNT | F15: GL Ref No. | G15: AGING(DAYS) | H15: RECON
D17: ADD: DEBIT IN OUR BOOKS BUT NOT CREDITED BY BOG
D20: TOTAL: | E20: =SUM($E$18:$E$19) -> 0
D23: ADD: DEBIT ORIGINATED BY BOG BUT NOT CREDITED IN OUR BOOKS
D26: TOTAL: | E26: =SUM($E$24:$E$25) -> 0
D29: LESS: CREDIT ORIGINATED BY BOG BUT NOT DEBITED IN OUR BOOKS
D32: TOTAL: | E32: =SUM($E$30:$E$31) -> 0
D35: LESS: CREDIT IN OUR BOOKS BUT NOT DEBITED BY BOG
D38: TOTAL: | E38: =SUM($E$36:$E$37) -> 0
D41: GRAND TOTAL | E41: =ABS(E13+$E$20-$E$38+$E$26-$E$32) -> 159835
D42: INTERNAL ACCOUNT BALANCE AS AT Nov 20, 2025 | E42: 159835 | I42: DR
D43: DIFFERENCE | E43: =$E$42-$E$41 -> 0
D45: PREPARED BY: | E45: kenneth nuamah | F45: DATE: | G45: 45981
D48: REVIEWED BY: | F48: DATE:

Sheet BOG TDI GBP
A1: Field_1 | B1: Field_2 | C1: Field_3 | D1: Field_4 | E1: Field_5 | F1: Field_6 | G1: Field_7 | H1: Field_8 | I1: Field_9 | J1: Field_10
B4: DEPT | D4: OPERATIONS | E4: BANK ACCOUNT NUMBER | F4: 3037231344014
B6: BRANCH | D6: HEAD OFFICE | E6: GENERAL LEDGER NAME | F6: BANK OF GHANA -TAKORADI- GBP
B8: REPORTING DATE | D8: 20-Nov-25 | E8: GENERAL LEDGER NUMBER | F8: 0040113730010
B10: REPORTING UNIT | D10: RECONCILIATION
C13: 2025-10-31 | D13: BALANCE PER BANK STATEMENT | E13: 14340 | I13: CR
B15: SN | C15: DATE | D15: DESCRIPTION | E15: AMOUNT | F15: GL Ref No. | G15: AGING(DAYS) | H15: RECON
D17: ADD: DEBIT IN OUR BOOKS BUT NOT CREDITED BY BOG
D20: TOTAL: | E20: =SUM($E$18:$E$19) -> 0
D23: ADD: DEBIT ORIGINATED BY BOG BUT NOT CREDITED IN OUR BOOKS
D26: TOTAL: | E26: =SUM($E$24:$E$25) -> 0
D29: LESS: CREDIT ORIGINATED BY BOG BUT NOT DEBITED IN OUR BOOKS
D32: TOTAL: | E32: =SUM($E$30:$E$31) -> 0
D35: LESS: CREDIT IN OUR BOOKS BUT NOT DEBITED BY BOG
D38: TOTAL: | E38: =SUM($E$36:$E$37) -> 0
D41: GRAND TOTAL | E41: =ABS(E13+$E$20-$E$38+$E$26-$E$32) -> 14340
D42: INTERNAL ACCOUNT BALANCE AS AT Nov 20, 2025 | E42: 14340 | I42: DR
D43: DIFFERENCE | E43: =$E$42-$E$41 -> 0
D45: PREPARED BY: | E45: kenneth nuamah | F45: DATE: | G45: 45981
D48: REVIEWED BY: | F48: DATE:

Sheet BOG TLE GHS
A1: Field_1 | B1: Field_2 | C1: Field_3 | D1: Field_4 | E1: Field_5 | F1: Field_6 | G1: Field_7 | H1: Field_8 | I1: Field_9 | J1: Field_10
B4: DEPT | D4: OPERATIONS | E4: BANK ACCOUNT NUMBER | F4: 5017231344018
B6: BRANCH | D6: HEAD OFFICE | E6: GENERAL LEDGER NAME | F6: BANK OF GHANA -TAMALE-GHS
B8: REPORTING DATE | D8: 20-Nov-25 | E8: GENERAL LEDGER NUMBER | F8: 0010000092019
B10: REPORTING UNIT | D10: RECONCILIATION
C13: 20-Nov-2025 | D13: BALANCE PER BANK STATEMENT | E13: 34296332 | I13: CR
B15: SN | C15: DATE | D15: DESCRIPTION | E15: AMOUNT | F15: GL Ref No. | G15: AGING(DAYS) | H15: RECON
D17: ADD: DEBIT IN OUR BOOKS BUT NOT CREDITED BY BOG
D20: TOTAL: | E20: =SUM($E$18:$E$19) -> 0
D23: ADD: DEBIT ORIGINATED BY BOG BUT NOT CREDITED IN OUR BOOKS
D26: TOTAL: | E26: =SUM($E$24:$E$25) -> 0
D29: LESS: CREDIT ORIGINATED BY BOG BUT NOT DEBITED IN OUR BOOKS
D32: TOTAL: | E32: =SUM($E$30:$E$31) -> 0
D35: LESS: CREDIT IN OUR BOOKS BUT NOT DEBITED BY BOG
D38: TOTAL: | E38: =SUM($E$36:$E$37) -> 0
D41: GRAND TOTAL | E41: =ABS(E13+$E$20-$E$38+$E$26-$E$32) -> 34296332
D42: INTERNAL ACCOUNT BALANCE AS AT Nov 20, 2025 | E42: 34296332 | I42: DR
D43: DIFFERENCE | E43: =$E$42-$E$41 -> 0
D45: PREPARED BY: | E45: kenneth nuamah | F45: DATE: | G45: 45981
D48: REVIEWED BY: | F48: DATE:

Sheet BOG TLE USD
A1: Field_1 | B1: Field_2 | C1: Field_3 | D1: Field_4 | E1: Field_5 | F1: Field_6 | G1: Field_7 | H1: Field_8 | I1: Field_9 | J1: Field_10
B4: DEPT | D4: OPERATIONS | E4: BANK ACCOUNT NUMBER | F4: 5027231344016
B6: BRANCH | D6: HEAD OFFICE | E6: GENERAL LEDGER NAME | F6: BANK OF GHANA -TAMALE-USD
B8: REPORTING DATE | D8: 20-Nov-25 | E8: GENERAL LEDGER NUMBER | F8: 0020000092016
B10: REPORTING UNIT | D10: RECONCILIATION
C13: 14-Nov-2025 | D13: BALANCE PER BANK STATEMENT | E13: 76000 | I13: CR
B15: SN | C15: DATE | D15: DESCRIPTION | E15: AMOUNT | F15: GL Ref No. | G15: AGING(DAYS) | H15: RECON
D17: ADD: DEBIT IN OUR BOOKS BUT NOT CREDITED BY BOG
D20: TOTAL: | E20: =SUM($E$18:$E$19) -> 0
D23: ADD: DEBIT ORIGINATED BY BOG BUT NOT CREDITED IN OUR BOOKS
D26: TOTAL: | E26: =SUM($E$24:$E$25) -> 0
D29: LESS: CREDIT ORIGINATED BY BOG BUT NOT DEBITED IN OUR BOOKS
D32: TOTAL: | E32: =SUM($E$30:$E$31) -> 0
D35: LESS: CREDIT IN OUR BOOKS BUT NOT DEBITED BY BOG
D38: TOTAL: | E38: =SUM($E$36:$E$37) -> 0
D41: GRAND TOTAL | E41: =ABS(E13+$E$20-$E$38+$E$26-$E$32) -> 76000
D42: INTERNAL ACCOUNT BALANCE AS AT Nov 20, 2025 | E42: 76000 | I42: DR
D43: DIFFERENCE | E43: =$E$42-$E$41 -> 0
D45: PREPARED BY: | E45: kenneth nuamah | F45: DATE: | G45: 45981
D48: REVIEWED BY: | F48: DATE:

Sheet BOG TLE EUR
A1: Field_1 | B1: Field_2 | C1: Field_3 | D1: Field_4 | E1: Field_5 | F1: Field_6 | G1: Field_7 | H1: Field_8 | I1: Field_9 | J1: Field_10
B4: DEPT | D4: OPERATIONS | E4: BANK ACCOUNT NUMBER | F4: 5187231344013
B6: BRANCH | D6: HEAD OFFICE | E6: GENERAL LEDGER NAME | F6: BANK OF GHANA -TAMALE-EUR
B8: REPORTING DATE | D8: 20-Nov-25 | E8: GENERAL LEDGER NUMBER | F8: 0030000092013
B10: REPORTING UNIT | D10: RECONCILIATION
C13: 14-Nov-2025 | D13: BALANCE PER BANK STATEMENT | E13: 500 | I13: CR
B15: SN | C15: DATE | D15: DESCRIPTION | E15: AMOUNT | F15: GL Ref No. | G15: AGING(DAYS) | H15: RECON
D17: ADD: DEBIT IN OUR BOOKS BUT NOT CREDITED BY BOG
D20: TOTAL: | E20: =SUM($E$18:$E$19) -> 0
D23: ADD: DEBIT ORIGINATED BY BOG BUT NOT CREDITED IN OUR BOOKS
D26: TOTAL: | E26: =SUM($E$24:$E$25) -> 0
D29: LESS: CREDIT ORIGINATED BY BOG BUT NOT DEBITED IN OUR BOOKS
D32: TOTAL: | E32: =SUM($E$30:$E$31) -> 0
D35: LESS: CREDIT IN OUR BOOKS BUT NOT DEBITED BY BOG
D38: TOTAL: | E38: =SUM($E$36:$E$37) -> 0
D41: GRAND TOTAL | E41: =ABS(E13+$E$20-$E$38+$E$26-$E$32) -> 500
D42: INTERNAL ACCOUNT BALANCE AS AT Nov 20, 2025 | E42: 500 | I42: DR
D43: DIFFERENCE | E43: =$E$42-$E$41 -> 0
D45: PREPARED BY: | E45: kenneth nuamah | F45: DATE: | G45: 45981
D48: REVIEWED BY: | F48: DATE:

Sheet BOG TLE GBP
A1: Field_1 | B1: Field_2 | C1: Field_3 | D1: Field_4 | E1: Field_5 | F1: Field_6 | G1: Field_7 | H1: Field_8 | I1: Field_9 | J1: Field_10
B4: DEPT | D4: OPERATIONS | E4: BANK ACCOUNT NUMBER | F4: 5187231344013
B6: BRANCH | D6: HEAD OFFICE | E6: GENERAL LEDGER NAME | F6: BANK OF GHANA -TAMALE-GBP
B8: REPORTING DATE | D8: 20-Nov-25 | E8: GENERAL LEDGER NUMBER | F8: 0030000092013
B10: REPORTING UNIT | D10: RECONCILIATION
C13: 2025-11-12 | D13: BALANCE PER BANK STATEMENT | E13: 0 | I13: CR
B15: SN | C15: DATE | D15: DESCRIPTION | E15: AMOUNT | F15: GL Ref No. | G15: AGING(DAYS) | H15: RECON
D17: ADD: DEBIT IN OUR BOOKS BUT NOT CREDITED BY BOG
D20: TOTAL: | E20: =SUM($E$18:$E$19) -> 0
D23: ADD: DEBIT ORIGINATED BY BOG BUT NOT CREDITED IN OUR BOOKS
D26: TOTAL: | E26: =SUM($E$24:$E$25) -> 0
D29: LESS: CREDIT ORIGINATED BY BOG BUT NOT DEBITED IN OUR BOOKS
D32: TOTAL: | E32: =SUM($E$30:$E$31) -> 0
D35: LESS: CREDIT IN OUR BOOKS BUT NOT DEBITED BY BOG
D38: TOTAL: | E38: =SUM($E$36:$E$37) -> 0
D41: GRAND TOTAL | E41: =ABS(E13+$E$20-$E$38+$E$26-$E$32) -> 0
D42: INTERNAL ACCOUNT BALANCE AS AT Nov 20, 2025 | E42: 0 | I42: DR
D43: DIFFERENCE | E43: =$E$42-$E$41 -> 0
D45: PREPARED BY: | E45: kenneth nuamah | F45: DATE: | G45: 45981
D48: REVIEWED BY: | F48: DATE:

Sheet AFRIEXIM EUR
A1: Field_1 | B1: Field_2 | C1: Field_3 | D1: Field_4 | E1: Field_5 | F1: Field_6 | G1: Field_7 | H1: Field_8 | I1: FIELD_9
B4: DEPT | D4: OPERATIONS | E4: BANK ACCOUNT NUMBER | F4: 300058801200001
B6: BRANCH | D6: HEAD OFFICE | E6: GENERAL LEDGER NAME | F6: AFRIEXIM EUR
B8: REPORTING DATE | D8: 20-Nov-25 | E8: GENERAL LEDGER NUMBER | F8: 0030000097017
B10: REPORTING UNIT | D10: RECONCILIATION
C13: 20-Nov-25 | D13: BALANCE PER BANK STATEMENT | E13: 0 | I13: DR
B15: SN | C15: DATE | D15: DESCRIPTION | E15: AMOUNT | F15: GL Ref No. | G15: AGING(DAYS) | H15: RECON
D17: ADD: DEBIT IN OUR BOOKS BUT NOT CREDITED BY AFRIEXIM
D20: TOTAL: | E20: =SUM($E$18:$E$19) -> 0
D23: ADD: DEBIT ORIGINATED BY AFRIEXIM BUT NOT CREDITED IN OUR BOOKS
D26: TOTAL: | E26: =SUM($E$24:$E$25) -> 0
D29: LESS: CREDIT ORIGINATED BY AFRIEXIM BUT NOT DEBITED IN OUR BOOKS
D32: TOTAL: | E32: =SUM($E$30:$E$31) -> 0
D35: LESS: CREDIT IN OUR BOOKS BUT NOT DEBITED BY AFRIEXIM
D38: TOTAL: | E38: =SUM($E$36:$E$37) -> 0
D41: GRAND TOTAL | E41: =ABS(E13+$E$20-$E$38+$E$26-$E$32) -> 0
D42: INTERNAL ACCOUNT BALANCE AS AT Nov 20, 2025 | E42: 0 | I42: DR
D43: DIFFERENCE | E43: =$E$42-$E$41 -> 0
D45: PREPARED BY: | E45: kenneth nuamah | F45: DATE: | G45: 45981
D48: REVIEWED BY: | F48: DATE:

Sheet AFRIEXIM GBP
A1: Field_1 | B1: Field_2 | C1: Field_3 | D1: Field_4 | E1: Field_5 | F1: Field_6 | G1: Field_7 | H1: Field_8 | I1: FIELD_9
B4: DEPT | D4: OPERATIONS | E4: BANK ACCOUNT NUMBER | F4: 300058801200001
B6: BRANCH | D6: HEAD OFFICE | E6: GENERAL LEDGER NAME | F6: AFRIEXIM GBP
B8: REPORTING DATE | D8: 20-Nov-25 | E8: GENERAL LEDGER NUMBER | F8: 0040000097014
B10: REPORTING UNIT | D10: RECONCILIATION
C13: 20-Nov-25 | D13: BALANCE PER BANK STATEMENT | E13: 2313 | I13: CR
B15: SN | C15: DATE | D15: DESCRIPTION | E15: AMOUNT | F15: GL Ref No. | G15: AGING(DAYS) | H15: RECON
D17: ADD: DEBIT IN OUR BOOKS BUT NOT CREDITED BY AFRIEXIM
D20: TOTAL: | E20: =SUM($E$18:$E$19) -> 0
D23: ADD: DEBIT ORIGINATED BY AFRIEXIM BUT NOT CREDITED IN OUR BOOKS
D26: TOTAL: | E26: =SUM($E$24:$E$25) -> 0
D29: LESS: CREDIT ORIGINATED BY AFRIEXIM BUT NOT DEBITED IN OUR BOOKS
D32: TOTAL: | E32: =SUM($E$30:$E$31) -> 0
D35: LESS: CREDIT IN OUR BOOKS BUT NOT DEBITED BY AFRIEXIM
D38: TOTAL: | E38: =SUM($E$36:$E$37) -> 0
D41: GRAND TOTAL | E41: =ABS(E13+$E$20-$E$38+$E$26-$E$32) -> 2313
D42: INTERNAL ACCOUNT BALANCE AS AT Nov 20, 2025 | E42: 2313 | I42: CR
D43: DIFFERENCE | E43: =$E$42-$E$41 -> 0
D45: PREPARED BY: | E45: kenneth nuamah | F45: DATE: | G45: 45981
D48: REVIEWED BY: | F48: DATE:

Sheet AFRIEXIM USD
A1: Field_1 | B1: Field_2 | C1: Field_3 | D1: Field_4 | E1: Field_5 | F1: Field_6 | G1: Field_7 | H1: Field_8 | I1: FIELD_9
B4: DEPT | D4: OPERATIONS | E4: BANK ACCOUNT NUMBER | F4: 300058801200001
B6: BRANCH | D6: HEAD OFFICE | E6: GENERAL LEDGER NAME | F6: AFRIEXIM USD
B8: REPORTING DATE | D8: 20-Nov-25 | E8: GENERAL LEDGER NUMBER
B10: REPORTING UNIT | D10: RECONCILIATION
C13: 20-Nov-25 | D13: BALANCE PER BANK STATEMENT | E13: 4692166.9 | I13: CR
B15: SN | C15: DATE | D15: DESCRIPTION | E15: AMOUNT | F15: GL Ref No. | G15: AGING(DAYS) | H15: RECON
D17: ADD: DEBIT IN OUR BOOKS BUT NOT CREDITED BY AFRIEXIM
B18: 1 | C18: 19-Nov-2025 | D18: FX PURCHASE - USD/GHS @ 11.0150 | E18: 100000 | F18: FX PURCHASE - USD/GHS @ 11.0150 | G18: 1 | H18: INT DR
B19: 2 | C19: 20-Nov-2025 | D19: FX PURCHASE - USD/GHS @ 11.00 | E19: 40000 | F19: 2532401436634000 | G19: 0 | H19: INT DR
B20: 3 | C20: 20-Nov-2025 | D20: FX PURCHASE - USD/GHS @ 11.12 - UNERGROUND MINING ALLIANCE | E20: 3000000 | F20: 000UMAG253240001 | G20: 0 | H20: INT DR
D22: TOTAL: | E22: =SUM($E$18:$E$21) -> 3140000
D25: ADD: DEBIT ORIGINATED BY AFRIEXIM BUT NOT CREDITED IN OUR BOOKS
D28: TOTAL: | E28: =SUM($E$26:$E$27) -> 0
D31: LESS: CREDIT ORIGINATED BY AFRIEXIM BUT NOT DEBITED IN OUR BOOKS
B32: 1 | C32: 12-Nov-2025 | D32: N MSC BEN:EG5290040001 //ORD:8700206114 SWIFT REF:2025111200385413. PO:000 | E32: 700000 | F32: N MSC BEN:EG5290040001 //ORD:8700206114 SWIFT REF:2025111200385413. PO:000 | G32: 8 | H32: EXT CR
B33: 2 | C33: 18-Nov-2025 | D33: 599360 BEN:3000588012 ORD SEG627921/19-11-2025/2 | E33: 3000000 | F33: 599360 BEN:3000588012 ORD SEG627921/19-11-2025/2 | G33: 2 | H33: EXT CR
B34: 3 | C34: 19-Nov-2025 | D34: 599360 BEN:3000588012 ORD SEG628241/19-11-2025/2 | E34: 40000 | F34: 599360 BEN:3000588012 ORD SEG628241/19-11-2025/2 | G34: 1 | H34: EXT CR
B35: 4 | C35: 19-Nov-2025 | D35: 599360 ORD:. Nm:Fast BEN SEG627829/19-11-2025/2 | E35: 100000 | F35: 599360 ORD:. Nm:Fast BEN SEG627829/19-11-2025/2 | G35: 1 | H35: EXT CR
B36: 5 | C36: 19-Nov-2025 | D36: 599982 BEN:3000588012 ORD SEG629677/20-11-2025/2 | E36: 300000 | F36: ORD | G36: 1 | H36: EXT CR
D38: TOTAL: | E38: =SUM($E$32:$E$37) -> 4140000
D41: LESS: CREDIT IN OUR BOOKS BUT NOT DEBITED BY AFRIEXIM
D44: TOTAL: | E44: =SUM($E$42:$E$43) -> 0
D47: GRAND TOTAL | E47: =ABS(E13+$E$22-$E$44+$E$28-$E$38) -> 3692166.9
D48: INTERNAL ACCOUNT BALANCE AS AT Nov 20, 2025 | E48: 3692166.9 | I48: DR
D49: DIFFERENCE | E49: =$E$48-$E$47 -> 0
D51: PREPARED BY: | E51: kenneth nuamah | F51: DATE: | G51: 45981
D54: REVIEWED BY: | F54: DATE:

Sheet AFRIEXIM USD PAPSS
A1: Field_1 | B1: Field_2 | C1: Field_3 | D1: Field_4 | E1: Field_5 | F1: Field_6 | G1: Field_7 | H1: Field_8 | I1: FIELD_9
B4: DEPT | D4: OPERATIONS | E4: BANK ACCOUNT NUMBER | F4: EG179004000100300058801803001
B6: BRANCH | D6: HEAD OFFICE | E6: GENERAL LEDGER NAME | F6: AFRICAN EXIM BANK USD - PAPSS
B8: REPORTING DATE | D8: 20-Nov-25 | E8: GENERAL LEDGER NUMBER | F8: 0020000097020
B10: REPORTING UNIT | D10: RECONCILIATION
C13: 20-Nov-25 | D13: BALANCE PER BANK STATEMENT | E13: 578.25 | I13: CR
B15: SN | C15: DATE | D15: DESCRIPTION | E15: AMOUNT | F15: GL Ref No. | G15: AGING(DAYS) | H15: RECON
D17: ADD: DEBIT IN OUR BOOKS BUT NOT CREDITED BY AFRIEXIM
D20: TOTAL: | E20: =SUM($E$18:$E$19) -> 0
D23: ADD: DEBIT ORIGINATED BY AFRIEXIM BUT NOT CREDITED IN OUR BOOKS
D26: TOTAL: | E26: =SUM($E$24:$E$25) -> 0
D29: LESS: CREDIT ORIGINATED BY AFRIEXIM BUT NOT DEBITED IN OUR BOOKS
B30: 1 | C30: 07-Nov-2025 | D30: N MSC //PAPPS PAPSS USD SETTLEMENT | E30: 68.49 | F30: N MSC //PAPPS PAPSS USD SETTLEMENT | G30: 13 | H30: EXT CR
D32: TOTAL: | E32: =SUM($E$30:$E$31) -> 68.49
D35: LESS: CREDIT IN OUR BOOKS BUT NOT DEBITED BY AFRIEXIM
D38: TOTAL: | E38: =SUM($E$36:$E$37) -> 0
D41: GRAND TOTAL | E41: =ABS(E13+$E$20-$E$38+$E$26-$E$32) -> 509.76
D42: INTERNAL ACCOUNT BALANCE AS AT Nov 20, 2025 | E42: 509.76 | I42: CR
D43: DIFFERENCE | E43: =$E$42-$E$41 -> 0
D45: PREPARED BY: | E45: kenneth nuamah | F45: DATE: | G45: 45981
D48: REVIEWED BY: | F48: DATE:

Sheet AKTIF EUR
A1: Field_1 | B1: Field_2 | C1: Field_3 | D1: Field_4 | E1: Field_5 | F1: Field_6 | G1: Field_7 | H1: Field_8 | I1: FIELD_9
B4: DEPT | D4: OPERATIONS | E4: BANK ACCOUNT NUMBER | F4: ^TR540014300000000007408441
B6: BRANCH | D6: HEAD OFFICE | E6: GENERAL LEDGER NAME | F6: AKTIF EUR
B8: REPORTING DATE | D8: 20-Nov-25 | E8: GENERAL LEDGER NUMBER | F8: 0020000139018
B10: REPORTING UNIT | D10: RECONCILIATION
C13: 20-Nov-25 | D13: BALANCE PER BANK STATEMENT | E13: 0.82 | I13: CR
B15: SN | C15: DATE | D15: DESCRIPTION | E15: AMOUNT | F15: GL Ref No. | G15: AGING(DAYS) | H15: RECON
D17: ADD: DEBIT IN OUR BOOKS BUT NOT CREDITED BY AKTIF
D20: TOTAL: | E20: =SUM($E$18:$E$19) -> 0
D23: ADD: DEBIT ORIGINATED BY AKTIF BUT NOT CREDITED IN OUR BOOKS
D26: TOTAL: | E26: =SUM($E$24:$E$25) -> 0
D29: LESS: CREDIT ORIGINATED BY AKTIF BUT NOT DEBITED IN OUR BOOKS
D32: TOTAL: | E32: =SUM($E$30:$E$31) -> 0
D35: LESS: CREDIT IN OUR BOOKS BUT NOT DEBITED BY AKTIF
D38: TOTAL: | E38: =SUM($E$36:$E$37) -> 0
D41: GRAND TOTAL | E41: =ABS(E13+$E$20-$E$38+$E$26-$E$32) -> 0.82
D42: INTERNAL ACCOUNT BALANCE AS AT Nov 20, 2025 | E42: 0.82 | I42: CR
D43: DIFFERENCE | E43: =$E$42-$E$41 -> 0
D45: PREPARED BY: | E45: kenneth nuamah | F45: DATE: | G45: 45981
D48: REVIEWED BY: | F48: DATE:

Sheet AKTIF GBP
A1: Field_1 | B1: Field_2 | C1: Field_3 | D1: Field_4 | E1: Field_5 | F1: Field_6 | G1: Field_7 | H1: Field_8 | I1: FIELD_9
B4: DEPT | D4: OPERATIONS | E4: BANK ACCOUNT NUMBER | F4: ^TR430014300000000007408445
B6: BRANCH | D6: HEAD OFFICE | E6: GENERAL LEDGER NAME | F6: AKTIF GBP
B8: REPORTING DATE | D8: 20-Nov-25 | E8: GENERAL LEDGER NUMBER | F8: 0040000139012
B10: REPORTING UNIT | D10: RECONCILIATION
C13: 20-Nov-25 | D13: BALANCE PER BANK STATEMENT | E13: 51970 | I13: CR
B15: SN | C15: DATE | D15: DESCRIPTION | E15: AMOUNT | F15: GL Ref No. | G15: AGING(DAYS) | H15: RECON
D17: ADD: DEBIT IN OUR BOOKS BUT NOT CREDITED BY AKTIF
D20: TOTAL: | E20: =SUM($E$18:$E$19) -> 0
D23: ADD: DEBIT ORIGINATED BY AKTIF BUT NOT CREDITED IN OUR BOOKS
D26: TOTAL: | E26: =SUM($E$24:$E$25) -> 0
D29: LESS: CREDIT ORIGINATED BY AKTIF BUT NOT DEBITED IN OUR BOOKS
D32: TOTAL: | E32: =SUM($E$30:$E$31) -> 0
D35: LESS: CREDIT IN OUR BOOKS BUT NOT DEBITED BY AKTIF
D38: TOTAL: | E38: =SUM($E$36:$E$37) -> 0
D41: GRAND TOTAL | E41: =ABS(E13+$E$20-$E$38+$E$26-$E$32) -> 51970
D42: INTERNAL ACCOUNT BALANCE AS AT Nov 20, 2025 | E42: 51970 | I42: CR
D43: DIFFERENCE | E43: =$E$42-$E$41 -> 0
D45: PREPARED BY: | E45: kenneth nuamah | F45: DATE: | G45: 45981
D48: REVIEWED BY: | F48: DATE:

Sheet AKTIF USD
A1: Field_1 | B1: Field_2 | C1: Field_3 | D1: Field_4 | E1: Field_5 | F1: Field_6 | G1: Field_7 | H1: Field_8 | I1: FIELD_9
B4: DEPT | D4: OPERATIONS | E4: BANK ACCOUNT NUMBER | F4: ^TR540014300000000007408441
B6: BRANCH | D6: HEAD OFFICE | E6: GENERAL LEDGER NAME | F6: AKTIF USD
B8: REPORTING DATE | D8: 20-Nov-25 | E8: GENERAL LEDGER NUMBER | F8: 0020000139018
B10: REPORTING UNIT | D10: RECONCILIATION
C13: 20-Nov-25 | D13: BALANCE PER BANK STATEMENT | E13: 336633.39 | I13: CR
B15: SN | C15: DATE | D15: DESCRIPTION | E15: AMOUNT | F15: GL Ref No. | G15: AGING(DAYS) | H15: RECON
D17: ADD: DEBIT IN OUR BOOKS BUT NOT CREDITED BY AKTIF
D20: TOTAL: | E20: =SUM($E$18:$E$19) -> 0
D23: ADD: DEBIT ORIGINATED BY AKTIF BUT NOT CREDITED IN OUR BOOKS
D26: TOTAL: | E26: =SUM($E$24:$E$25) -> 0
D29: LESS: CREDIT ORIGINATED BY AKTIF BUT NOT DEBITED IN OUR BOOKS
D32: TOTAL: | E32: =SUM($E$30:$E$31) -> 0
D35: LESS: CREDIT IN OUR BOOKS BUT NOT DEBITED BY AKTIF
D38: TOTAL: | E38: =SUM($E$36:$E$37) -> 0
D41: GRAND TOTAL | E41: =ABS(E13+$E$20-$E$38+$E$26-$E$32) -> 336633.39
D42: INTERNAL ACCOUNT BALANCE AS AT Nov 20, 2025 | E42: 336633.39 | I42: CR
D43: DIFFERENCE | E43: =$E$42-$E$41 -> 0
D45: PREPARED BY: | E45: kenneth nuamah | F45: DATE: | G45: 45981
D48: REVIEWED BY: | F48: DATE:

Sheet ARAB TURKISH EUR
A1: Field_1 | B1: Field_2 | C1: Field_3 | D1: Field_4 | E1: Field_5 | F1: Field_6 | G1: Field_7 | H1: Field_8 | I1: FIELD_9
B4: DEPT | D4: OPERATIONS | E4: BANK ACCOUNT NUMBER | F4: 32000019867
B6: BRANCH | D6: HEAD OFFICE | E6: GENERAL LEDGER NAME | F6: ARAB TURKISH BANK - EUR
B8: REPORTING DATE | D8: 20-Nov-25 | E8: GENERAL LEDGER NUMBER | F8: 0030000089019
B10: REPORTING UNIT | D10: RECONCILIATION
C13: 20-Nov-25 | D13: BALANCE PER BANK STATEMENT | E13: 2158890.1 | I13: CR
B15: SN | C15: DATE | D15: DESCRIPTION | E15: AMOUNT | F15: GL Ref No. | G15: AGING(DAYS) | H15: RECON
D17: ADD: DEBIT IN OUR BOOKS BUT NOT CREDITED BY ARAB TURKISH BANK
D20: TOTAL: | E20: =SUM($E$18:$E$19) -> 0
D23: ADD: DEBIT ORIGINATED BY ARAB TURKISH BANK BUT NOT CREDITED IN OUR BOOKS
D26: TOTAL: | E26: =SUM($E$24:$E$25) -> 0
D29: LESS: CREDIT ORIGINATED BY ARAB TURKISH BANK BUT NOT DEBITED IN OUR BOOKS
B30: 1 | C30: 19-Nov-2025 | D30: 20251119-248 FT2532300293 FT2532300293 | E30: 48.05 | F30: 20251119-248 FT2532300293 FT2532300293 | G30: 1 | H30: EXT CR
B31: 2 | C31: 20-Nov-2025 | D31: 20251120-249 FT2532400307 TRANSFER | E31: 1.47 | F31: TRANSFER | G31: 0 | H31: EXT CR
D33: TOTAL: | E33: =SUM($E$30:$E$32) -> 49.52
D36: LESS: CREDIT IN OUR BOOKS BUT NOT DEBITED BY ARAB TURKISH BANK
D39: TOTAL: | E39: =SUM($E$37:$E$38) -> 0
D42: GRAND TOTAL | E42: =ABS(E13+$E$20-$E$39+$E$26-$E$33) -> 2158840.6
D43: INTERNAL ACCOUNT BALANCE AS AT Nov 20, 2025 | E43: 2158840.6 | I43: DR
D44: DIFFERENCE | E44: =$E$43-$E$42 -> 0
D46: PREPARED BY: | E46: kenneth nuamah | F46: DATE: | G46: 45981
D49: REVIEWED BY: | F49: DATE:

Sheet ARAB TURKISH USD
A1: Field_1 | B1: Field_2 | C1: Field_3 | D1: Field_4 | E1: Field_5 | F1: Field_6 | G1: Field_7 | H1: Field_8 | I1: FIELD_9
B4: DEPT | D4: OPERATIONS | E4: BANK ACCOUNT NUMBER | F4: 32000029245
B6: BRANCH | D6: HEAD OFFICE | E6: GENERAL LEDGER NAME | F6: ARAB TURKISH BANK - USD
B8: REPORTING DATE | D8: 20-Nov-25 | E8: GENERAL LEDGER NUMBER | F8: 0020000089011
B10: REPORTING UNIT | D10: RECONCILIATION
C13: 20-Nov-25 | D13: BALANCE PER BANK STATEMENT | E13: 77332.97 | I13: CR
B15: SN | C15: DATE | D15: DESCRIPTION | E15: AMOUNT | F15: GL Ref No. | G15: AGING(DAYS) | H15: RECON
D17: ADD: DEBIT IN OUR BOOKS BUT NOT CREDITED BY ARAB TURKISH BANK
D20: TOTAL: | E20: =SUM($E$18:$E$19) -> 0
D23: ADD: DEBIT ORIGINATED BY ARAB TURKISH BANK BUT NOT CREDITED IN OUR BOOKS
D26: TOTAL: | E26: =SUM($E$24:$E$25) -> 0
D29: LESS: CREDIT ORIGINATED BY ARAB TURKISH BANK BUT NOT DEBITED IN OUR BOOKS
D32: TOTAL: | E32: =SUM($E$30:$E$31) -> 0
D35: LESS: CREDIT IN OUR BOOKS BUT NOT DEBITED BY ARAB TURKISH BANK
D38: TOTAL: | E38: =SUM($E$36:$E$37) -> 0
D41: GRAND TOTAL | E41: =ABS(E13+$E$20-$E$38+$E$26-$E$32) -> 77332.97
D42: INTERNAL ACCOUNT BALANCE AS AT Nov 20, 2025 | E42: 77332.97 | I42: CR
D43: DIFFERENCE | E43: =$E$42-$E$41 -> 0
D45: PREPARED BY: | E45: kenneth nuamah | F45: DATE: | G45: 45981
D48: REVIEWED BY: | F48: DATE:

Sheet BANK OF BEIRUT EUR
A1: Field_1 | B1: Field_2 | C1: Field_3 | D1: Field_4 | E1: Field_5 | F1: Field_6 | G1: Field_7 | H1: Field_8 | I1: FIELD_9
B4: DEPT | D4: OPERATIONS | E4: BANK ACCOUNT NUMBER | F4: ^4016093345900
B6: BRANCH | D6: HEAD OFFICE | E6: GENERAL LEDGER NAME | F6: BANK OF BEIRUT EUR
B8: REPORTING DATE | D8: 20-Nov-25 | E8: GENERAL LEDGER NUMBER | F8: 0030000099012
B10: REPORTING UNIT | D10: RECONCILIATION
C13: 20-Nov-25 | D13: BALANCE PER BANK STATEMENT | E13: 0 | I13: DR
B15: SN | C15: DATE | D15: DESCRIPTION | E15: AMOUNT | F15: GL Ref No. | G15: AGING(DAYS) | H15: RECON
D17: ADD: DEBIT IN OUR BOOKS BUT NOT CREDITED BY BEIRUT
D20: TOTAL: | E20: =SUM($E$18:$E$19) -> 0
D23: ADD: DEBIT ORIGINATED BY BEIRUT BUT NOT CREDITED IN OUR BOOKS
D26: TOTAL: | E26: =SUM($E$24:$E$25) -> 0
D29: LESS: CREDIT ORIGINATED BY BEIRUT BUT NOT DEBITED IN OUR BOOKS
D32: TOTAL: | E32: =SUM($E$30:$E$31) -> 0
D35: LESS: CREDIT IN OUR BOOKS BUT NOT DEBITED BY BEIRUT
D38: TOTAL: | E38: =SUM($E$36:$E$37) -> 0
D41: GRAND TOTAL | E41: =ABS(E13+$E$20-$E$38+$E$26-$E$32) -> 0
D42: INTERNAL ACCOUNT BALANCE AS AT Nov 20, 2025 | E42: 0 | I42: DR
D43: DIFFERENCE | E43: =$E$42-$E$41 -> 0
D45: PREPARED BY: | E45: kenneth nuamah | F45: DATE: | G45: 45981
D48: REVIEWED BY: | F48: DATE:

Sheet BANK OF BEIRUT GBP
A1: Field_1 | B1: Field_2 | C1: Field_3 | D1: Field_4 | E1: Field_5 | F1: Field_6 | G1: Field_7 | H1: Field_8 | I1: FIELD_9
B4: DEPT | D4: OPERATIONS | E4: BANK ACCOUNT NUMBER | F4: ^0116093345900
B6: BRANCH | D6: HEAD OFFICE | E6: GENERAL LEDGER NAME | F6: BANK OF BEIRUT GBP
B8: REPORTING DATE | D8: 20-Nov-25 | E8: GENERAL LEDGER NUMBER | F8: 0040000099018
B10: REPORTING UNIT | D10: RECONCILIATION
C13: 20-Nov-25 | D13: BALANCE PER BANK STATEMENT | E13: 0 | I13: DR
B15: SN | C15: DATE | D15: DESCRIPTION | E15: AMOUNT | F15: GL Ref No. | G15: AGING(DAYS) | H15: RECON
D17: ADD: DEBIT IN OUR BOOKS BUT NOT CREDITED BY BEIRUT
D20: TOTAL: | E20: =SUM($E$18:$E$19) -> 0
D23: ADD: DEBIT ORIGINATED BY BEIRUT BUT NOT CREDITED IN OUR BOOKS
D26: TOTAL: | E26: =SUM($E$24:$E$25) -> 0
D29: LESS: CREDIT ORIGINATED BY BEIRUT BUT NOT DEBITED IN OUR BOOKS
D32: TOTAL: | E32: =SUM($E$30:$E$31) -> 0
D35: LESS: CREDIT IN OUR BOOKS BUT NOT DEBITED BY BEIRUT
D38: TOTAL: | E38: =SUM($E$36:$E$37) -> 0
D41: GRAND TOTAL | E41: =ABS(E13+$E$20-$E$38+$E$26-$E$32) -> 0
D42: INTERNAL ACCOUNT BALANCE AS AT Nov 20, 2025 | E42: 0 | I42: DR
D43: DIFFERENCE | E43: =$E$42-$E$41 -> 0
D45: PREPARED BY: | E45: kenneth nuamah | F45: DATE: | G45: 45981
D48: REVIEWED BY: | F48: DATE:

Sheet BANK OF BEIRUT USD
A1: Field_1 | B1: Field_2 | C1: Field_3 | D1: Field_4 | E1: Field_5 | F1: Field_6 | G1: Field_7 | H1: Field_8 | I1: FIELD_9
B4: DEPT | D4: OPERATIONS | E4: BANK ACCOUNT NUMBER | F4: ^1116093345900
B6: BRANCH | D6: HEAD OFFICE | E6: GENERAL LEDGER NAME | F6: BANK OF BEIRUT USD
B8: REPORTING DATE | D8: 20-Nov-25 | E8: GENERAL LEDGER NUMBER | F8: 0020000099015
B10: REPORTING UNIT | D10: RECONCILIATION
C13: 20-Nov-25 | D13: BALANCE PER BANK STATEMENT | E13: 4668031.8 | I13: CR
B15: SN | C15: DATE | D15: DESCRIPTION | E15: AMOUNT | F15: GL Ref No. | G15: AGING(DAYS) | H15: RECON
D17: ADD: DEBIT IN OUR BOOKS BUT NOT CREDITED BY BEIRUT
D20: TOTAL: | E20: =SUM($E$18:$E$19) -> 0
D23: ADD: DEBIT ORIGINATED BY BEIRUT BUT NOT CREDITED IN OUR BOOKS
D26: TOTAL: | E26: =SUM($E$24:$E$25) -> 0
D29: LESS: CREDIT ORIGINATED BY BEIRUT BUT NOT DEBITED IN OUR BOOKS
D32: TOTAL: | E32: =SUM($E$30:$E$31) -> 0
D35: LESS: CREDIT IN OUR BOOKS BUT NOT DEBITED BY BEIRUT
D38: TOTAL: | E38: =SUM($E$36:$E$37) -> 0
D41: GRAND TOTAL | E41: =ABS(E13+$E$20-$E$38+$E$26-$E$32) -> 4668031.8
D42: INTERNAL ACCOUNT BALANCE AS AT Nov 20, 2025 | E42: 4668031.8 | I42: CR
D43: DIFFERENCE | E43: =$E$42-$E$41 -> 0
D45: PREPARED BY: | E45: kenneth nuamah | F45: DATE: | G45: 45981
D48: REVIEWED BY: | F48: DATE:

Sheet COTE DVOIRE XOF
A1: Field_1 | B1: Field_2 | C1: Field_3 | D1: Field_4 | E1: Field_5 | F1: Field_6 | G1: Field_7 | H1: Field_8 | I1: FIELD_9
B4: DEPT | D4: OPERATIONS | E4: BANK ACCOUNT NUMBER | F4: 99951400001
B6: BRANCH | D6: HEAD OFFICE | E6: GENERAL LEDGER NAME | F6: BSIC COTE D'IVOIRE - XOF
B8: REPORTING DATE | D8: 20-Nov-25 | E8: GENERAL LEDGER NUMBER | F8: 0050154485011
B10: REPORTING UNIT | D10: RECONCILIATION
C13: 20-Nov-25 | D13: BALANCE PER BANK STATEMENT | E13: 6570525 | I13: CR
B15: SN | C15: DATE | D15: DESCRIPTION | E15: AMOUNT | F15: GL Ref No. | G15: AGING(DAYS) | H15: RECON
D17: ADD: DEBIT IN OUR BOOKS BUT NOT CREDITED BY COTE D'IVOIRE
D20: TOTAL: | E20: =SUM($E$18:$E$19) -> 0
D23: ADD: DEBIT ORIGINATED BY COTE D'IVOIRE BUT NOT CREDITED IN OUR BOOKS
D26: TOTAL: | E26: =SUM($E$24:$E$25) -> 0
D29: LESS: CREDIT ORIGINATED BY COTE D'IVOIRE BUT NOT DEBITED IN OUR BOOKS
D32: TOTAL: | E32: =SUM($E$30:$E$31) -> 0
D35: LESS: CREDIT IN OUR BOOKS BUT NOT DEBITED BY COTE D'IVOIRE
D38: TOTAL: | E38: =SUM($E$36:$E$37) -> 0
D41: GRAND TOTAL | E41: =ABS(E13+$E$20-$E$38+$E$26-$E$32) -> 6570525
D42: INTERNAL ACCOUNT BALANCE AS AT Nov 20, 2025 | E42: 6570525 | I42: CR
D43: DIFFERENCE | E43: =$E$42-$E$41 -> 0
D45: PREPARED BY: | E45: kenneth nuamah | F45: DATE: | G45: 45981
D48: REVIEWED BY: | F48: DATE:

Sheet ECOBANK
A1: Field_1 | B1: Field_2 | C1: Field_3 | D1: Field_4 | E1: Field_5 | F1: Field_6 | G1: Field_7 | H1: Field_8 | I1: FIELD_9
B4: DEPT | D4: OPERATIONS | E4: BANK ACCOUNT NUMBER | F4: 1441001256551
B6: BRANCH | D6: HEAD OFFICE | E6: GENERAL LEDGER NAME | F6: ECOBANK
B8: REPORTING DATE | D8: 20-Nov-25 | E8: GENERAL LEDGER NUMBER | F8: 0010000094014
B10: REPORTING UNIT | D10: RECONCILIATION
C13: 20-Nov-25 | D13: BALANCE PER BANK STATEMENT | E13: 2623086.9 | I13: CR
B15: SN | C15: DATE | D15: DESCRIPTION | E15: AMOUNT | F15: GL Ref No. | G15: AGING(DAYS) | H15: RECON
D17: ADD: DEBIT IN OUR BOOKS BUT NOT CREDITED BY ECOBANK
D20: TOTAL: | E20: =SUM($E$18:$E$19) -> 0
D23: ADD: DEBIT ORIGINATED BY ECOBANK BUT NOT CREDITED IN OUR BOOKS
D26: TOTAL: | E26: =SUM($E$24:$E$25) -> 0
D29: LESS: CREDIT ORIGINATED BY ECOBANK BUT NOT DEBITED IN OUR BOOKS
D32: TOTAL: | E32: =SUM($E$30:$E$31) -> 0
D35: LESS: CREDIT IN OUR BOOKS BUT NOT DEBITED BY ECOBANK
D38: TOTAL: | E38: =SUM($E$36:$E$37) -> 0
D41: GRAND TOTAL | E41: =ABS(E13+$E$20-$E$38+$E$26-$E$32) -> 2623086.9
D42: INTERNAL ACCOUNT BALANCE AS AT Nov 20, 2025 | E42: 2623086.9 | I42: CR
D43: DIFFERENCE | E43: =$E$42-$E$41 -> 0
D45: PREPARED BY: | E45: kenneth nuamah | F45: DATE: | G45: 45981
D48: REVIEWED BY: | F48: DATE:

Sheet GCB
A1: Field_1 | B1: Field_2 | C1: Field_3 | D1: Field_4 | E1: Field_5 | F1: Field_6 | G1: Field_7 | H1: Field_8 | I1: FIELD_9
B4: DEPT | D4: OPERATIONS | E4: BANK ACCOUNT NUMBER | F4: ^1331130004604
B6: BRANCH | D6: HEAD OFFICE | E6: GENERAL LEDGER NAME | F6: GCB
B8: REPORTING DATE | D8: 20-Nov-25 | E8: GENERAL LEDGER NUMBER | F8: 0010000095017
B10: REPORTING UNIT | D10: RECONCILIATION
C13: 20-Nov-25 | D13: BALANCE PER BANK STATEMENT | E13: 11414017 | I13: CR
B15: SN | C15: DATE | D15: DESCRIPTION | E15: AMOUNT | F15: GL Ref No. | G15: AGING(DAYS) | H15: RECON
D17: ADD: DEBIT IN OUR BOOKS BUT NOT CREDITED BY GCB
D20: TOTAL: | E20: =SUM($E$18:$E$19) -> 0
D23: ADD: DEBIT ORIGINATED BY GCB BUT NOT CREDITED IN OUR BOOKS
D26: TOTAL: | E26: =SUM($E$24:$E$25) -> 0
D29: LESS: CREDIT ORIGINATED BY GCB BUT NOT DEBITED IN OUR BOOKS
B30: 1 | C30: 16-Sep-2025 | D30: ZENITH BANK GH CHQ - UIC JESUS KIDS DAY CARE CENTRE~002363 - DEP NTRE~002363 - DEP. AT CAPECOAST AT CAPECOAST | E30: 5359.25 | G30: 65 | H30: EXT CR
B31: 2 | C31: 02-Oct-2025 | D31: ZENITH BANK GH CHQ - MIKONVILL INFANTS SCHOOL~000922 - DEP. AT C 00922 - DEP. AT CAPECOAST PECOAST | E31: 9775 | G31: 49 | H31: EXT CR
B32: 3 | C32: 13-Oct-2025 | D32: AGRICULTURAL DEVELOPMENT CHQ - CALVARY HILLCREST SCHOOLS BOOKS ACCOUNT~000096 - DEP. AT CAPECOAST | E32: 5525 | G32: 38 | H32: EXT CR
D34: TOTAL: | E34: =SUM($E$30:$E$33) -> 20659.25
D37: LESS: CREDIT IN OUR BOOKS BUT NOT DEBITED BY GCB
D40: TOTAL: | E40: =SUM($E$38:$E$39) -> 0
D43: GRAND TOTAL | E43: =ABS(E13+$E$20-$E$40+$E$26-$E$34) -> 11393357
D44: INTERNAL ACCOUNT BALANCE AS AT Nov 20, 2025 | E44: 11393357 | I44: DR
D45: DIFFERENCE | E45: =$E$44-$E$43 -> 0
D47: PREPARED BY: | E47: kenneth nuamah | F47: DATE: | G47: 45981
D50: REVIEWED BY: | F50: DATE:

Sheet GCB 2 & 3
A1: Field_1 | B1: Field_2 | C1: Field_3 | D1: Field_4 | E1: Field_5 | F1: Field_6 | G1: Field_7 | H1: Field_8 | I1: FIELD_9
B4: DEPT | D4: OPERATIONS | E4: BANK ACCOUNT NUMBER | F4: '1151130006048
B6: BRANCH | D6: HEAD OFFICE | E6: GENERAL LEDGER NAME | F6: GCB BANK LTD 3
B8: REPORTING DATE | D8: 20-Nov-25 | E8: GENERAL LEDGER NUMBER
B10: REPORTING UNIT | D10: RECONCILIATION
C13: 20-Nov-25 | D13: BALANCE PER BANK STATEMENT | E13: 411946.93 | I13: CR
B15: SN | C15: DATE | D15: DESCRIPTION | E15: AMOUNT | F15: GL Ref No. | G15: AGING(DAYS) | H15: RECON
D17: ADD: DEBIT IN OUR BOOKS BUT NOT CREDITED BY GCB
D20: TOTAL: | E20: =SUM($E$18:$E$19) -> 0
D23: ADD: DEBIT ORIGINATED BY GCB BUT NOT CREDITED IN OUR BOOKS
D26: TOTAL: | E26: =SUM($E$24:$E$25) -> 0
D29: LESS: CREDIT ORIGINATED BY GCB BUT NOT DEBITED IN OUR BOOKS
D32: TOTAL: | E32: =SUM($E$30:$E$31) -> 0
D35: LESS: CREDIT IN OUR BOOKS BUT NOT DEBITED BY GCB
D38: TOTAL: | E38: =SUM($E$36:$E$37) -> 0
D41: GRAND TOTAL | E41: =ABS(E13+$E$20-$E$38+$E$26-$E$32) -> 411946.93
D42: INTERNAL ACCOUNT BALANCE AS AT Nov 20, 2025 | E42: 411946.93 | I42: CR
D43: DIFFERENCE | E43: =$E$42-$E$41 -> 0
D45: PREPARED BY: | E45: kenneth nuamah | F45: DATE: | G45: 45981
D48: REVIEWED BY: | F48: DATE:

Sheet GHIB EUR
A1: Field_1 | B1: Field_2 | C1: Field_3 | D1: Field_4 | E1: Field_5 | F1: Field_6 | G1: Field_7 | H1: Field_8 | I1: FIELD_9
B4: DEPT | D4: OPERATIONS | E4: BANK ACCOUNT NUMBER | F4: ^51162603
B6: BRANCH | D6: HEAD OFFICE | E6: GENERAL LEDGER NAME | F6: GHIB - EUR
B8: REPORTING DATE | D8: 20-Nov-25 | E8: GENERAL LEDGER NUMBER | F8: 0030000032011
B10: REPORTING UNIT | D10: RECONCILIATION
C13: 20-Nov-25 | D13: BALANCE PER BANK STATEMENT | E13: 1369750.5 | I13: CR
B15: SN | C15: DATE | D15: DESCRIPTION | E15: AMOUNT | F15: GL Ref No. | G15: AGING(DAYS) | H15: RECON
D17: ADD: DEBIT IN OUR BOOKS BUT NOT CREDITED BY GHIB
B18: 1 | C18: 20-Nov-2025 | D18: FX PURCHASE EUR, XOF @ 669.07614038462 000FXSP253240501 | E18: 520000 | F18: 000FXSP253240501 | G18: 0 | H18: INT DR
D20: TOTAL: | E20: =SUM($E$18:$E$19) -> 520000
D23: ADD: DEBIT ORIGINATED BY GHIB BUT NOT CREDITED IN OUR BOOKS
B24: 1 | C24: 12-Nov-2025 | D24: N TRF OMNOPA20251053 //FT2531600471 Outward Telex Payment | E24: 39060 | F24: OMNOPA20251053 | G24: 8 | H24: EXT DR
B25: 2 | C25: 13-Nov-2025 | D25: 20251113-204 FT2531756740 OMNTR20251789 | E25: 38.5 | F25: OMNTR20251789 | G25: 7 | H25: EXT DR
B26: 3 | C26: 14-Nov-2025 | D26: 20251114-205 FT2531896640 OMNAP20254337 | E26: 38.5 | F26: OMNAP20254337 | G26: 6 | H26: EXT DR
B27: 4 | C27: 17-Nov-2025 | D27: 20251117-206 FT2532141252 OMNAP20254128R | E27: 38.5 | F27: OMNAP20254128R | G27: 3 | H27: EXT DR
B28: 5 | C28: 19-Nov-2025 | D28: 20251119-208 FT2532306347 OMNTR20251831 | E28: 38.5 | F28: OMNTR20251831 | G28: 1 | H28: EXT DR
B29: 6 | C29: 19-Nov-2025 | D29: 20251119-208 FT2532306347 OMNTR20251831 | E29: 504.25 | F29: OMNTR20251831 | G29: 1 | H29: EXT DR
B30: 7 | C30: 20-Nov-2025 | D30: 20251120-209 FT2532404194 OMNAP20254437 | E30: 22 | F30: OMNAP20254437 | G30: 0 | H30: EXT DR
B31: 8 | C31: 20-Nov-2025 | D31: 20251120-209 FT2532493040 OMNAP20254431 | E31: 38.5 | F31: OMNAP20254431 | G31: 0 | H31: EXT DR
B32: 9 | C32: 20-Nov-2025 | D32: 20251120-209 FT2532493040 OMNAP20254431 | E32: 4659 | F32: OMNAP20254431 | G32: 0 | H32: EXT DR
D34: TOTAL: | E34: =SUM($E$24:$E$33) -> 44437.75
D37: LESS: CREDIT ORIGINATED BY GHIB BUT NOT DEBITED IN OUR BOOKS
B38: 1 | C38: 05-Nov-2025 | D38: N TRF NONREF //FT2530979005 Outward Telex Payment | E38: 2221.64 | F38: N TRF NONREF //FT2530979005 Outward Telex Payment | G38: 15 | H38: EXT CR
D40: TOTAL: | E40: =SUM($E$38:$E$39) -> 2221.64
D43: LESS: CREDIT IN OUR BOOKS BUT NOT DEBITED BY GHIB
B44: 1 | C44: 20-Nov-2025 | D44: OMNTR20251870 TRF IFO EKOAGROS | E44: 250 | F44: OMNTR20251870 | G44: 0 | H44: INT CR
B45: 2 | C45: 20-Nov-2025 | D45: OMNTR20251873 TRF IFO STEPHANIE PEARL ADAMS | E45: 1000 | F45: OMNTR20251873 | G45: 0 | H45: INT CR
B46: 3 | C46: 20-Nov-2025 | D46: OMNTR20251866 TRF IFO T MARK CONSEILS | E46: 5510 | F46: OMNTR20251866 | G46: 0 | H46: INT CR
B47: 4 | C47: 20-Nov-2025 | D47: OMNAP20254482 TRF IFO KIKA LT UAB | E47: 11646 | F47: OMNAP20254482 | G47: 0 | H47: INT CR
B48: 5 | C48: 20-Nov-2025 | D48: OMNOPA20251081 TRF IFO T.C.M DI TORTORA GAETANO & C.S.R.L | E48: 41514.16 | F48: OMNOPA20251081 | G48: 0 | H48: INT CR
D50: TOTAL: | E50: =SUM($E$44:$E$49) -> 59920.16
D53: GRAND TOTAL | E53: =ABS(E13+$E$20-$E$50+$E$34-$E$40) -> 1872046.4
D54: INTERNAL ACCOUNT BALANCE AS AT Nov 20, 2025 | E54: 1872046.4 | I54: DR
D55: DIFFERENCE | E55: =$E$54-$E$53 -> 0
D57: PREPARED BY: | E57: kenneth nuamah | F57: DATE: | G57: 45981
D60: REVIEWED BY: | F60: DATE:

Sheet GHIB GBP
A1: Field_1 | B1: Field_2 | C1: Field_3 | D1: Field_4 | E1: Field_5 | F1: Field_6 | G1: Field_7 | H1: Field_8 | I1: FIELD_9
B4: DEPT | D4: OPERATIONS | E4: BANK ACCOUNT NUMBER | F4: ^51162601
B6: BRANCH | D6: HEAD OFFICE | E6: GENERAL LEDGER NAME | F6: GHIB - GBP
B8: REPORTING DATE | D8: 20-Nov-25 | E8: GENERAL LEDGER NUMBER | F8: 0040000032019
B10: REPORTING UNIT | D10: RECONCILIATION
C13: 20-Nov-25 | D13: BALANCE PER BANK STATEMENT | E13: 320144.76 | I13: CR
B15: SN | C15: DATE | D15: DESCRIPTION | E15: AMOUNT | F15: GL Ref No. | G15: AGING(DAYS) | H15: RECON
D17: ADD: DEBIT IN OUR BOOKS BUT NOT CREDITED BY GHIB
D20: TOTAL: | E20: =SUM($E$18:$E$19) -> 0
D23: ADD: DEBIT ORIGINATED BY GHIB BUT NOT CREDITED IN OUR BOOKS
B24: 1 | C24: 14-Nov-2025 | D24: 20251114-205 FT2531816475 OMNTR20251801 | E24: 10 | F24: OMNTR20251801 | G24: 6 | H24: EXT DR
B25: 2 | C25: 14-Nov-2025 | D25: 20251114-205 FT2531831366 OMNTR20251803 | E25: 10 | F25: OMNTR20251803 | G25: 6 | H25: EXT DR
B26: 3 | C26: 14-Nov-2025 | D26: 20251114-205 FT2531830281 OMNTR20251804 | E26: 10 | F26: OMNTR20251804 | G26: 6 | H26: EXT DR
B27: 4 | C27: 17-Nov-2025 | D27: 20251117-206 FT2532120258 OMNAP20254328 | E27: 10 | F27: OMNAP20254328 | G27: 3 | H27: EXT DR
B28: 5 | C28: 17-Nov-2025 | D28: 20251117-206 FT2532156605 OMNAP20254388 | E28: 10 | F28: OMNAP20254388 | G28: 3 | H28: EXT DR
B29: 6 | C29: 17-Nov-2025 | D29: 20251117-206 FT2532115999 OMNTR20251797 | E29: 10 | F29: OMNTR20251797 | G29: 3 | H29: EXT DR
B30: 7 | C30: 17-Nov-2025 | D30: 20251117-206 FT2531835790 OMNTR20251805 | E30: 10 | F30: OMNTR20251805 | G30: 3 | H30: EXT DR
B31: 8 | C31: 17-Nov-2025 | D31: 20251117-206 FT2532166186 OMNTR20251808 | E31: 10 | F31: OMNTR20251808 | G31: 3 | H31: EXT DR
B32: 9 | C32: 17-Nov-2025 | D32: 20251117-206 FT2532115999 OMNTR20251797 | E32: 4500 | F32: OMNTR20251797 | G32: 3 | H32: EXT DR
B33: 10 | C33: 17-Nov-2025 | D33: 20251117-206 FT2532156605 OMNAP20254388 | E33: 17000 | F33: OMNAP20254388 | G33: 3 | H33: EXT DR
B34: 11 | C34: 18-Nov-2025 | D34: 20251118-207 FT2532230527 OMNTR20251822 | E34: 10 | F34: OMNTR20251822 | G34: 2 | H34: EXT DR
B35: 12 | C35: 18-Nov-2025 | D35: 20251118-207 FT2532272915 OMNTR20251829 | E35: 10 | F35: OMNTR20251829 | G35: 2 | H35: EXT DR
... B38: 15 | C38: 19-Nov-2025 | D38: 20251119-208 FT2532368518 OMNAP20254434 | E38: 5800.75 | F38: OMNAP20254434 | G38: 1 | H38: EXT DR
D40: TOTAL: | E40: =SUM($E$24:$E$39) -> 27420.75
D43: LESS: CREDIT ORIGINATED BY GHIB BUT NOT DEBITED IN OUR BOOKS
D46: TOTAL: | E46: =SUM($E$44:$E$45) -> 0
D49: LESS: CREDIT IN OUR BOOKS BUT NOT DEBITED BY GHIB
B50: 1 | C50: 20-Nov-2025 | D50: OMNTR20251867 TRF IFO OFFSETK SERVICES LLP | E50: 2565 | F50: OMNTR20251867 | G50: 0 | H50: INT CR
D52: TOTAL: | E52: =SUM($E$50:$E$51) -> 2565
D55: GRAND TOTAL | E55: =ABS(E13+$E$20-$E$52+$E$40-$E$46) -> 345000.51
D56: INTERNAL ACCOUNT BALANCE AS AT Nov 20, 2025 | E56: 345000.51 | I56: DR
D57: DIFFERENCE | E57: =$E$56-$E$55 -> 0
D59: PREPARED BY: | E59: kenneth nuamah | F59: DATE: | G59: 45981
D62: REVIEWED BY: | F62: DATE:

Sheet GHIB USD
A1: Field_1 | B1: Field_2 | C1: Field_3 | D1: Field_4 | E1: Field_5 | F1: Field_6 | G1: Field_7 | H1: Field_8 | I1: FIELD_9
B4: DEPT | D4: OPERATIONS | E4: BANK ACCOUNT NUMBER | F4: ^51162602
B6: BRANCH | D6: HEAD OFFICE | E6: GENERAL LEDGER NAME | F6: GHIB - USD
B8: REPORTING DATE | D8: 20-Nov-25 | E8: GENERAL LEDGER NUMBER | F8: 0020000032014
B10: REPORTING UNIT | D10: RECONCILIATION
C13: 20-Nov-25 | D13: BALANCE PER BANK STATEMENT | E13: 14016043 | I13: CR
B15: SN | C15: DATE | D15: DESCRIPTION | E15: AMOUNT | F15: GL Ref No. | G15: AGING(DAYS) | H15: RECON
D17: ADD: DEBIT IN OUR BOOKS BUT NOT CREDITED BY GHIB
B18: 1 | C18: 20-Nov-2025 | D18: TRSF03201125GHIB TEXT | E18: 5 | F18: TRSF03201125GHIB | G18: 0 | H18: INT DR
D20: TOTAL: | E20: =SUM($E$18:$E$19) -> 5
D23: ADD: DEBIT ORIGINATED BY GHIB BUT NOT CREDITED IN OUR BOOKS
B24: 1 | C24: 12-Nov-2025 | D24: F CHG OMNTR20251778 //FT2531647756 Outward Telex-Swift Charges | E24: 35 | F24: OMNTR20251778 | G24: 8 | H24: EXT DR
B25: 2 | C25: 14-Nov-2025 | D25: 20251114-205 FT2531814180 ALC25/0646XMAE00 | E25: 327.73 | F25: 20251114-205 FT2531814180 ALC25/0646XMAE00 | G25: 6 | H25: EXT DR
B26: 3 | C26: 17-Nov-2025 | D26: 20251117-206 FT2532106239 OMNAP20254109 | E26: 70000 | F26: OMNAP20254109 | G26: 3 | H26: EXT DR
D28: TOTAL: | E28: =SUM($E$24:$E$27) -> 70362.73
D31: LESS: CREDIT ORIGINATED BY GHIB BUT NOT DEBITED IN OUR BOOKS
B32: 1 | C32: 19-Nov-2025 | D32: 20251119-208 FT2532330755 NONREF | E32: 1092.35 | F32: 20251119-208 FT2532330755 NONREF | G32: 1 | H32: EXT CR
B33: 2 | C33: 20-Nov-2025 | D33: 20251120-209 FT2532400300 NONREF | E33: 1025.84 | F33: NONREF | G33: 0 | H33: EXT CR
D35: TOTAL: | E35: =SUM($E$32:$E$34) -> 2118.19
D38: LESS: CREDIT IN OUR BOOKS BUT NOT DEBITED BY GHIB
B39: 1 | C39: 11-Nov-2025 | D39: 2531501345912000;TRF IFO ROBERT ACKWONU | E39: 1 | F39: 2531501345912000;TRF IFO ROBERT ACKWONU | G39: 9 | H39: INT CR
B40: 2 | C40: 12-Nov-2025 | D40: 2531601357102000_TRANSFER | E40: 1 | F40: 2531601357102000_TRANSFER | G40: 8 | H40: INT CR
B41: 3 | C41: 14-Nov-2025 | D41: TRANSFER | E41: 1 | F41: TRANSFER | G41: 6 | H41: INT CR
B42: 4 | C42: 14-Nov-2025 | D42: TRANSFER | E42: 1 | F42: TRANSFER | G42: 6 | H42: INT CR
B43: 5 | C43: 14-Nov-2025 | D43: TRANSFER | E43: 1 | F43: TRANSFER | G43: 6 | H43: INT CR
B44: 6 | C44: 19-Nov-2025 | D44: OMNAP20254388 ; TRF IFO SAVILE ROW ONLINE LTD | E44: 4500 | F44: OMNAP20254388 | G44: 1 | H44: INT CR
B45: 7 | C45: 19-Nov-2025 | D45: OMNTR20251797 ; TRF IFO GRACE ASARE | E45: 17000 | F45: OMNTR20251797 | G45: 1 | H45: INT CR
B46: 8 | C46: 19-Nov-2025 | D46: OMNAP20254130 TRF IFO CHANGJU CO LIMITED | E46: 70000 | F46: OMNAP20254130 | G46: 1 | H46: INT CR
B47: 9 | C47: 20-Nov-2025 | D47: TRSF04201125UBA TEXT | E47: 6 | F47: TRSF04201125UBA | G47: 0 | H47: INT CR
D49: TOTAL: | E49: =SUM($E$39:$E$48) -> 91511
D52: GRAND TOTAL | E52: =ABS(E13+$E$20-$E$49+$E$28-$E$35) -> 13992782
D53: INTERNAL ACCOUNT BALANCE AS AT Nov 20, 2025 | E53: 13992782 | I53: DR
D54: DIFFERENCE | E54: =$E$53-$E$52 -> 0
D56: PREPARED BY: | E56: kenneth nuamah | F56: DATE: | G56: 45981
D59: REVIEWED BY: | F59: DATE:

Sheet HEAD OFFICE USD
A1: Field_1 | B1: Field_2 | C1: Field_3 | D1: Field_4 | E1: Field_5 | F1: Field_6 | G1: Field_7 | H1: Field_8 | I1: FIELD_9
B4: DEPT | D4: OPERATIONS | E4: BANK ACCOUNT NUMBER | F4: 999514-000
B6: BRANCH | D6: HEAD OFFICE | E6: GENERAL LEDGER NAME | F6: BSIC HEAD OFFICE - USD
B8: REPORTING DATE | D8: 20-Nov-25 | E8: GENERAL LEDGER NUMBER | F8: 0020121317019
B10: REPORTING UNIT | D10: RECONCILIATION
C13: 20-Nov-25 | D13: BALANCE PER BANK STATEMENT | E13: 2848.49 | I13: CR
B15: SN | C15: DATE | D15: DESCRIPTION | E15: AMOUNT | F15: GL Ref No. | G15: AGING(DAYS) | H15: RECON
D17: ADD: DEBIT IN OUR BOOKS BUT NOT CREDITED BY BSIC HEAD OFFICE
D20: TOTAL: | E20: =SUM($E$18:$E$19) -> 0
D23: ADD: DEBIT ORIGINATED BY BSIC HEAD OFFICE BUT NOT CREDITED IN OUR BOOKS
B24: 1 | C24: 29-Sep-2020 | D24: SETTL.INT (SHO/MED LOANS) - BSIC AF 29-09-2020 | E24: 1435.2 | F24: SETTL.INT (SHO/MED LOANS) - BSIC AF 29-09-2020 | G24: 1878 | H24: EXT DR
D26: TOTAL: | E26: =SUM($E$24:$E$25) -> 1435.2
D29: LESS: CREDIT ORIGINATED BY BSIC HEAD OFFICE BUT NOT DEBITED IN OUR BOOKS
D32: TOTAL: | E32: =SUM($E$30:$E$31) -> 0
D35: LESS: CREDIT IN OUR BOOKS BUT NOT DEBITED BY BSIC HEAD OFFICE
D38: TOTAL: | E38: =SUM($E$36:$E$37) -> 0
D41: GRAND TOTAL | E41: =ABS(E13+$E$20-$E$38+$E$26-$E$32) -> 4283.69
D42: INTERNAL ACCOUNT BALANCE AS AT Nov 20, 2025 | E42: 4283.69 | I42: CR
D43: DIFFERENCE | E43: =$E$42-$E$41 -> 0
D45: PREPARED BY: | E45: kenneth nuamah | F45: DATE: | G45: 45981
D48: REVIEWED BY: | F48: DATE:

Sheet SENEGAL XOF
A1: Field_1 | B1: Field_2 | C1: Field_3 | D1: Field_4 | E1: Field_5 | F1: Field_6 | G1: Field_7 | H1: Field_8 | I1: FIELD_9
B4: DEPT | D4: OPERATIONS | E4: BANK ACCOUNT NUMBER | F4: 99951500001
B6: BRANCH | D6: HEAD OFFICE | E6: GENERAL LEDGER NAME | F6: BSIC SENEGAL- XOF
B8: REPORTING DATE | D8: 20-Nov-25 | E8: GENERAL LEDGER NUMBER | F8: 0050121363018
B10: REPORTING UNIT | D10: RECONCILIATION
C13: 20-Nov-25 | D13: BALANCE PER BANK STATEMENT | E13: 60 | I13: CR
B15: SN | C15: DATE | D15: DESCRIPTION | E15: AMOUNT | F15: GL Ref No. | G15: AGING(DAYS) | H15: RECON
D17: ADD: DEBIT IN OUR BOOKS BUT NOT CREDITED BY SENEGAL
D20: TOTAL: | E20: =SUM($E$18:$E$19) -> 0
D23: ADD: DEBIT ORIGINATED BY SENEGAL BUT NOT CREDITED IN OUR BOOKS
D26: TOTAL: | E26: =SUM($E$24:$E$25) -> 0
D29: LESS: CREDIT ORIGINATED BY SENEGAL BUT NOT DEBITED IN OUR BOOKS
D32: TOTAL: | E32: =SUM($E$30:$E$31) -> 0
D35: LESS: CREDIT IN OUR BOOKS BUT NOT DEBITED BY SENEGAL
D38: TOTAL: | E38: =SUM($E$36:$E$37) -> 0
D41: GRAND TOTAL | E41: =ABS(E13+$E$20-$E$38+$E$26-$E$32) -> 60
D42: INTERNAL ACCOUNT BALANCE AS AT Nov 20, 2025 | E42: 60 | I42: CR
D43: DIFFERENCE | E43: =$E$42-$E$41 -> 0
D45: PREPARED BY: | E45: kenneth nuamah | F45: DATE: | G45: 45981
D48: REVIEWED BY: | F48: DATE:

Sheet TOGO XOF
A1: Field_1 | B1: Field_2 | C1: Field_3 | D1: Field_4 | E1: Field_5 | F1: Field_6 | G1: Field_7 | H1: Field_8 | I1: FIELD_9
B4: DEPT | D4: OPERATIONS | E4: BANK ACCOUNT NUMBER | F4: 01500063921-24
B6: BRANCH | D6: HEAD OFFICE | E6: GENERAL LEDGER NAME | F6: BSIC TOGO - XOF
B8: REPORTING DATE | D8: 20-Nov-25 | E8: GENERAL LEDGER NUMBER | F8: 0050000091015
B10: REPORTING UNIT | D10: RECONCILIATION
C13: 20-Nov-25 | D13: BALANCE PER BANK STATEMENT | E13: 1705613957 | I13: CR
B15: SN | C15: DATE | D15: DESCRIPTION | E15: AMOUNT | F15: GL Ref No. | G15: AGING(DAYS) | H15: RECON
D17: ADD: DEBIT IN OUR BOOKS BUT NOT CREDITED BY TOGO
B18: 1 | C18: 19-Nov-2025 | D18: SOFTCARE TRANSFER IFO YAHE-KADDSH SARL U | E18: 14745000 | F18: 000TOGO253230001 | G18: 1 | H18: INT DR
D20: TOTAL: | E20: =SUM($E$18:$E$19) -> 14745000
D23: ADD: DEBIT ORIGINATED BY TOGO BUT NOT CREDITED IN OUR BOOKS
B24: 1 | C24: 12-Nov-2025 | D24: TGKBANI001 VR300000671 000671 T03 TRANSFERT RECU | E24: 545500 | F24: VR300000671 | G24: 8 | H24: EXT DR
B25: 2 | C25: 12-Nov-2025 | D25: TGKBANI001 VR300000670 000670 T03 TRANSFERT RECU | E25: 1205500 | F25: VR300000670 | G25: 8 | H25: EXT DR
B26: 3 | C26: 14-Nov-2025 | D26: TGKBANI001 VR300000672 000672 T03 TRANSFERT RECU | E26: 10005500 | F26: VR300000672 | G26: 6 | H26: EXT DR
B27: 4 | C27: 19-Nov-2025 | D27: TGKBANI001 VR300000675 000675 T03 TRANSFERT RECU | E27: 10005500 | F27: VR300000675 | G27: 1 | H27: EXT DR
B28: 5 | C28: 19-Nov-2025 | D28: TGKBANI001 VR300000674 000674 T03 TRANSFERT RECU | E28: 500005500 | F28: VR300000674 | G28: 1 | H28: EXT DR
D30: TOTAL: | E30: =SUM($E$24:$E$29) -> 521767500
D33: LESS: CREDIT ORIGINATED BY TOGO BUT NOT DEBITED IN OUR BOOKS
B34: 1 | C34: 11-Nov-2025 | D34: TGE.ELW001 SB213089975 089975 354 TRANSFER FUNDS/KANE-EM INDUSTR | E34: 2000000 | F34: SB213089975 | G34: 9 | H34: EXT CR
B35: 2 | C35: 12-Nov-2025 | D35: TGA.ZEI001 SB211090242 090242 354 ANNULATION ECRITUR DU 111125 | E35: 2000000 | F35: SB211090242 | G35: 8 | H35: EXT CR
B36: 3 | C36: 17-Nov-2025 | D36: TGE.ELW001 SB213090603 090603 354 TRANSFER FUNDS/KEDA (GHANA) CE | E36: 9350000 | F36: SB213090603 | G36: 3 | H36: EXT CR
B37: 4 | C37: 18-Nov-2025 | D37: TGA.ZEI001 SB213090819 090819 354 TRANSFER OF FUNDS/SOFTCARE FM | E37: 5191000 | F37: SB213090819 | G37: 2 | H37: EXT CR
B38: 5 | C38: 18-Nov-2025 | D38: TGA.ZEI001 SB213090823 090823 354 TRANSFER OF FUNDS/GHANDOUR | E38: 8410132 | F38: SB213090823 | G38: 2 | H38: EXT CR
B39: 6 | C39: 18-Nov-2025 | D39: TGA.ZEI001 SB213090731 090731 354 TRANSFER OF FUNDS/SOFTCARE FM | E39: 14475000 | F39: SB213090731 | G39: 2 | H39: EXT CR
B40: 7 | C40: 18-Nov-2025 | D40: TGA.ZEI001 SB213090820 090820 354 TRANSFER OF FUNDS/SOFTCARE FM | E40: 14475000 | F40: SB213090820 | G40: 2 | H40: EXT CR
B41: 8 | C41: 18-Nov-2025 | D41: TGA.ZEI001 SB213090821 090821 354 TRANSFER OF FUNDS/SOFTCARE FM | E41: 35576000 | F41: SB213090821 | G41: 2 | H41: EXT CR
B42: 9 | C42: 20-Nov-2025 | D42: TGA.ZEI001 SB213091251 091251 354 TRANSFER OF FUNDS/SOFTCARE FM | E42: 17500 | F42: SB213091251 | G42: 0 | H42: EXT CR
B43: 10 | C43: 20-Nov-2025 | D43: TGA.ZEI001 SB213091242 091242 354 TRANSFER OF FUNDS/SUNDA GHANA | E43: 165300 | F43: SB213091242 | G43: 0 | H43: EXT CR
B44: 11 | C44: 20-Nov-2025 | D44: TGA.ZEI001 SB213091247 091247 354 TRANSFER OF FUNDS/SUNDA GHANA | E44: 298350 | F44: SB213091247 | G44: 0 | H44: EXT CR
B45: 12 | C45: 20-Nov-2025 | D45: TGA.ZEI001 SB213091235 091235 354 TRANSFER OF FUNDS/SUNDA GHANA | E45: 775200 | F45: SB213091235 | G45: 0 | H45: EXT CR
... B70: 37 | C70: 20-Nov-2025 | D70: TGA.ZEI001 SB191091096 091096 354 PAIEMENT FACT DABO/NUTRIFOODS | E70: 341804817 | F70: SB191091096 | G70: 0 | H70: EXT CR
D72: TOTAL: | E72: =SUM($E$34:$E$71) -> 613105064
D75: LESS: CREDIT IN OUR BOOKS BUT NOT DEBITED BY TOGO
B76: 1 | C76: 11-Nov-2025 | D76: OMNTR20251777;TRF IFO KOUDADJE KOFFI MENSAH | E76: 540000 | F76: OMNTR20251777 | G76: 9 | H76: INT CR
B77: 2 | C77: 11-Nov-2025 | D77: OMNTR20251776; TRF IFO KOUDADJE KOFFI MENSAH | E77: 1200000 | F77: OMNTR20251776 | G77: 9 | H77: INT CR
B78: 3 | C78: 17-Nov-2025 | D78: OMNTR20251825 TRF IFO BURKINA FASO CHAMBER OF COMMERCE | E78: 500000000 | F78: 0010117278014 | G78: 3 | H78: INT CR
B79: 4 | C79: 18-Nov-2025 | D79: OMNTR20251840 TRF IFO ROTARY DISTRICT 9103-ACD ET GALA | E79: 10000000 | F79: OMNTR20251840 | G79: 2 | H79: INT CR
B80: 5 | C80: 20-Nov-2025 | D80: OMNTR20251856 TRF IFO KAKOU ANGE PACOME | E80: 360000 | F80: OMNTR20251856 | G80: 0 | H80: INT CR
B81: 6 | C81: 20-Nov-2025 | D81: OMNTR20251859 TRF IFO WAGUEI SOULEYMANE | E81: 390000 | F81: OMNTR20251859 | G81: 0 | H81: INT CR
B82: 7 | C82: 20-Nov-2025 | D82: OMNTR20251857 TRF IFO MME DAGO MOUNYA OUELEKO | E82: 540000 | F82: OMNTR20251857 | G82: 0 | H82: INT CR
B83: 8 | C83: 20-Nov-2025 | D83: OMNTR20251858 TRF IFO MME DAGO MOUNYA OUELEKO | E83: 540000 | F83: OMNTR20251858 | G83: 0 | H83: INT CR
B84: 9 | C84: 20-Nov-2025 | D84: OMNTR20251862 TRF IFO GHADBOUN HADI | E84: 750000 | F84: OMNTR20251862 | G84: 0 | H84: INT CR
B85: 10 | C85: 20-Nov-2025 | D85: OMNTR20251860 TRF IFO KPOKPA LEKAGNON YANNICK | E85: 780000 | F85: OMNTR20251860 | G85: 0 | H85: INT CR
B86: 11 | C86: 20-Nov-2025 | D86: OMNTR20251864 TRF IFO KOUDADJE KOFFI MENSAH | E86: 1920000 | F86: OMNTR20251864 | G86: 0 | H86: INT CR
D88: TOTAL: | E88: =SUM($E$76:$E$87) -> 517020000
D91: GRAND TOTAL | E91: =ABS(E13+$E$20-$E$88+$E$30-$E$72) -> 1112001393
D92: INTERNAL ACCOUNT BALANCE AS AT Nov 20, 2025 | E92: 1112001393 | I92: DR
D93: DIFFERENCE | E93: =$E$92-$E$91 -> 0
D95: PREPARED BY: | E95: kenneth nuamah | F95: DATE: | G95: 45981
D98: REVIEWED BY: | F98: DATE:

Sheet UBA NY EUR
A1: Field_1 | B1: Field_2 | C1: Field_3 | D1: Field_4 | E1: Field_5 | F1: Field_6 | G1: Field_7 | H1: Field_8 | I1: FIELD_9
B4: DEPT | D4: OPERATIONS | E4: BANK ACCOUNT NUMBER | F4: 50010010004770
B6: BRANCH | D6: HEAD OFFICE | E6: GENERAL LEDGER NAME | F6: UBA NEW YORK EUR
B8: REPORTING DATE | D8: 20-Nov-25 | E8: GENERAL LEDGER NUMBER | F8: 0030000093016
B10: REPORTING UNIT | D10: RECONCILIATION
C13: 20-Nov-25 | D13: BALANCE PER BANK STATEMENT | E13: 802683.48 | I13: CR
B15: SN | C15: DATE | D15: DESCRIPTION | E15: AMOUNT | F15: GL Ref No. | G15: AGING(DAYS) | H15: RECON
D17: ADD: DEBIT IN OUR BOOKS BUT NOT CREDITED BY UBA
D20: TOTAL: | E20: =SUM($E$18:$E$19) -> 0
D23: ADD: DEBIT ORIGINATED BY UBA BUT NOT CREDITED IN OUR BOOKS
B24: 1 | C24: 12-Nov-2025 | D24: PTC FEE-OMNAP20254243 | E24: 35 | F24: OMNAP20254243 | G24: 8 | H24: EXT DR
B25: 2 | C25: 12-Nov-2025 | D25: PTC FEE-OMNAP20254316 | E25: 35 | F25: OMNAP20254316 | G25: 8 | H25: EXT DR
B26: 3 | C26: 12-Nov-2025 | D26: PTC FEE-OMNAP20254284 | E26: 35 | F26: OMNAP20254284 | G26: 8 | H26: EXT DR
B27: 4 | C27: 12-Nov-2025 | D27: PTC FEE-OMNAP20254303 | E27: 35 | F27: OMNAP20254303 | G27: 8 | H27: EXT DR
B28: 5 | C28: 12-Nov-2025 | D28: PTC FEE-OMNAP20254308 | E28: 35 | F28: OMNAP20254308 | G28: 8 | H28: EXT DR
B29: 6 | C29: 12-Nov-2025 | D29: PTC FEE-OMNOPA20251045 | E29: 35 | F29: OMNOPA20251045 | G29: 8 | H29: EXT DR
B30: 7 | C30: 12-Nov-2025 | D30: PTC FEE-OMNTR20251763 | E30: 35 | F30: OMNTR20251763 | G30: 8 | H30: EXT DR
B31: 8 | C31: 12-Nov-2025 | D31: PTC FEE-OMNAP20254323 | E31: 35 | F31: OMNAP20254323 | G31: 8 | H31: EXT DR
B32: 9 | C32: 13-Nov-2025 | D32: 50010010004770 NY105 PTC FEE-OMNAP202 PTC FEE-OMNAP20254269 | E32: 35 | F32: OMNAP202 | G32: 7 | H32: EXT DR
B33: 10 | C33: 13-Nov-2025 | D33: 50010010004770 NY22 PTC FEE-OMNAP202 PTC FEE-OMNAP20254315 | E33: 35 | F33: OMNAP202 | G33: 7 | H33: EXT DR
B34: 11 | C34: 13-Nov-2025 | D34: 50010010004770 NY194 PTC FEE-OMNAP202 PTC FEE-OMNAP20254366 | E34: 35 | F34: OMNAP202 | G34: 7 | H34: EXT DR
B35: 12 | C35: 17-Nov-2025 | D35: 50010010004770 NY111 PTC FEE-OMNAP202 PTC FEE-OMNAP20254255 | E35: 35 | F35: OMNAP202 | G35: 3 | H35: EXT DR
... B37: 14 | C37: 20-Nov-2025 | D37: 50010010004770 NY111 PTC FEE-OMNAP202 PTC FEE-OMNAP20254418 | E37: 35 | F37: OMNAP20254418 | G37: 0 | H37: EXT DR
D39: TOTAL: | E39: =SUM($E$24:$E$38) -> 490
D42: LESS: CREDIT ORIGINATED BY UBA BUT NOT DEBITED IN OUR BOOKS
D45: TOTAL: | E45: =SUM($E$43:$E$44) -> 0
D48: LESS: CREDIT IN OUR BOOKS BUT NOT DEBITED BY UBA
B49: 1 | C49: 11-Nov-2025 | D49: OMNOPA20251053; TRF IFO TRANSMARE CHEMIE NV | E49: 39060 | F49: OMNOPA20251053 | G49: 9 | H49: INT CR
B50: 2 | C50: 17-Nov-2025 | D50: PAYMENT FOR SITTING ALLOWANCE FOR THE FINANCE, OPERATIONS & IT BOARD SUB COMMITTEE DD 13.11.2025 | E50: 504.25 | F50: PAYMENT FOR SITTING ALLOWANCE FOR THE FINANCE, OPERATIONS & IT BOARD SUB COMMITTEE DD 13.11.2025 | G50: 3 | H50: INT CR
B51: 3 | C51: 18-Nov-2025 | D51: TRANSFER | E51: 4659 | F51: TRANSFER | G51: 2 | H51: INT CR
B52: 4 | C52: 19-Nov-2025 | D52: OMNTR20251852 TRF IFO EUROPEAN COLLEGE OF INNOVATION(ECI) LTD | E52: 3350 | F52: OMNTR20251852 | G52: 1 | H52: INT CR
B53: 5 | C53: 19-Nov-2025 | D53: OMNOPA20251085 TRF IFO IMBALLAGGI WEST AFRICA | E53: 48097 | F53: OMNOPA20251085 | G53: 1 | H53: INT CR
B54: 6 | C54: 19-Nov-2025 | D54: OMNAP20254463 TRF IFO KARL GEUTHER HANDELS- GMBH & CO.KG | E54: 50772 | F54: OMNAP20254463 | G54: 1 | H54: INT CR
B55: 7 | C55: 20-Nov-2025 | D55: OMNOPA20251091 ; TRF IFO SYMRISE GRANDA S.A.U | E55: 2362 | F55: OMNOPA20251091 | G55: 0 | H55: INT CR
B56: 8 | C56: 20-Nov-2025 | D56: OMNOPA20251086 ; TRF IFO CLAYTON FINANCE LTD | E56: 13016 | F56: OMNOPA20251086 | G56: 0 | H56: INT CR
B57: 9 | C57: 20-Nov-2025 | D57: OMNOPA20251079 TRF IFO UNIVERSAL PACK S.R.L | E57: 17247.78 | F57: OMNOPA20251079 | G57: 0 | H57: INT CR
D59: TOTAL: | E59: =SUM($E$49:$E$58) -> 179068.03
D62: GRAND TOTAL | E62: =ABS(E13+$E$20-$E$59+$E$39-$E$45) -> 624105.45
D63: INTERNAL ACCOUNT BALANCE AS AT Nov 20, 2025 | E63: 624105.45 | I63: DR
D64: DIFFERENCE | E64: =$E$63-$E$62 -> 0
D66: PREPARED BY: | E66: kenneth nuamah | F66: DATE: | G66: 45981
D69: REVIEWED BY: | F69: DATE:

Sheet UBA NY GBP
A1: Field_1 | B1: Field_2 | C1: Field_3 | D1: Field_4 | E1: Field_5 | F1: Field_6 | G1: Field_7 | H1: Field_8 | I1: FIELD_9
B4: DEPT | D4: OPERATIONS | E4: BANK ACCOUNT NUMBER | F4: 50010010004787
B6: BRANCH | D6: HEAD OFFICE | E6: GENERAL LEDGER NAME | F6: UBA NEW YORK GBP
B8: REPORTING DATE | D8: 20-Nov-25 | E8: GENERAL LEDGER NUMBER | F8: 0040000093013
B10: REPORTING UNIT | D10: RECONCILIATION
C13: 20-Nov-25 | D13: BALANCE PER BANK STATEMENT | E13: 68702.88 | I13: CR
B15: SN | C15: DATE | D15: DESCRIPTION | E15: AMOUNT | F15: GL Ref No. | G15: AGING(DAYS) | H15: RECON
D17: ADD: DEBIT IN OUR BOOKS BUT NOT CREDITED BY UBA
B18: 1 | C18: 20-Nov-2025 | D18: 251119084050 ; INFLOW B/O ASIANIC LTD IRO ASIAALINONE 2025071717630217 FFC | E18: 3835.55 | F18: 251119084050 | G18: 0 | H18: INT DR
D20: TOTAL: | E20: =SUM($E$18:$E$19) -> 3835.55
D23: ADD: DEBIT ORIGINATED BY UBA BUT NOT CREDITED IN OUR BOOKS
D26: TOTAL: | E26: =SUM($E$24:$E$25) -> 0
D29: LESS: CREDIT ORIGINATED BY UBA BUT NOT DEBITED IN OUR BOOKS
B30: 1 | C30: 18-Nov-2025 | D30: 50010010004787 NY135 ROC NATION SPORT ROC NATION SPORTS LIMITED-202511180000641 | E30: 1125 | F30: 202511180000641 | G30: 2 | H30: EXT CR
B31: 2 | C31: 19-Nov-2025 | D31: 50010010004787 NY130 ASIANIC LIMITED- ASIANIC LIMITED-202511190000053 | E31: 3835.55 | F31: 202511190000053 | G31: 1 | H31: EXT CR
D33: TOTAL: | E33: =SUM($E$30:$E$32) -> 4960.55
D36: LESS: CREDIT IN OUR BOOKS BUT NOT DEBITED BY UBA
B37: 1 | C37: 14-Nov-2025 | D37: OMNTR20251797;TRF IFO GRACE ASARE | E37: 4500 | F37: OMNTR20251797 | G37: 6 | H37: INT CR
B38: 2 | C38: 14-Nov-2025 | D38: OMNAP20254388 ; TRF IFO SAVILE ROW ONLINE LTD | E38: 17000 | F38: OMNAP20254388 | G38: 6 | H38: INT CR
B39: 3 | C39: 18-Nov-2025 | D39: OMNAP20254434 ; TRF IFO BESPOKE KITCHENS SOLUTIONS LTD | E39: 5800.75 | F39: OMNAP20254434 | G39: 2 | H39: INT CR
D41: TOTAL: | E41: =SUM($E$37:$E$40) -> 27300.75
D44: GRAND TOTAL | E44: =ABS(E13+$E$20-$E$41+$E$26-$E$33) -> 40277.13
D45: INTERNAL ACCOUNT BALANCE AS AT Nov 20, 2025 | E45: 40277.13 | I45: DR
D46: DIFFERENCE | E46: =$E$45-$E$44 -> 0
D48: PREPARED BY: | E48: kenneth nuamah | F48: DATE: | G48: 45981
D51: REVIEWED BY: | F51: DATE:

Sheet UBA NY USD
A1: Field_1 | B1: Field_2 | C1: Field_3 | D1: Field_4 | E1: Field_5 | F1: Field_6 | G1: Field_7 | H1: Field_8 | I1: FIELD_9
B4: DEPT | D4: OPERATIONS | E4: BANK ACCOUNT NUMBER | F4: 50010010004763
B6: BRANCH | D6: HEAD OFFICE | E6: GENERAL LEDGER NAME | F6: UBA NEW YORK USD
B8: REPORTING DATE | D8: 20-Nov-25 | E8: GENERAL LEDGER NUMBER | F8: 0020000093019
B10: REPORTING UNIT | D10: RECONCILIATION
C13: 20-Nov-25 | D13: BALANCE PER BANK STATEMENT | E13: 22326286 | I13: CR
B15: SN | C15: DATE | D15: DESCRIPTION | E15: AMOUNT | F15: GL Ref No. | G15: AGING(DAYS) | H15: RECON
D17: ADD: DEBIT IN OUR BOOKS BUT NOT CREDITED BY UBA
B18: 1 | C18: 19-Nov-2025 | D18: REV OMNAP20254388 ; TRF IFO SAVILE ROW ONLINE LTD | E18: 4500 | F18: OMNAP20254388 | G18: 1 | H18: INT DR
B19: 2 | C19: 19-Nov-2025 | D19: 7 DY USD MM PLACEMENT - GCB MM CONTRACT LIQUIDATION | E19: 6805.56 | F19: 7 DY USD MM PLACEMENT - GCB MM CONTRACT LIQUIDATION | G19: 1 | H19: INT DR
B20: 3 | C20: 19-Nov-2025 | D20: REV OMNTR20251797 ; TRF IFO GRACE ASARE | E20: 17000 | F20: OMNTR20251797 | G20: 1 | H20: INT DR
B21: 4 | C21: 20-Nov-2025 | D21: TRSF04201125UBA TEXT | E21: 6 | F21: TRSF04201125UBA | G21: 0 | H21: INT DR
B22: 5 | C22: 20-Nov-2025 | D22: 199326.366706 ; INFLOW B/O TRAVELSCAPE LLC IRO POP HOTEL SUPPLIER PAYMENT | E22: 798.85 | F22: 199326.366706 | G22: 0 | H22: INT DR
B23: 6 | C23: 20-Nov-2025 | D23: 1199287.366706 ; IFO TRAVELSCAPE LLC IRO POP HOTEL SUPPLIER PAYMENT | E23: 1569.2 | F23: 1199287.366706 | G23: 0 | H23: INT DR
B24: 7 | C24: 20-Nov-2025 | D24: FX PURCHASE USD, GHS @ 11.10 000FXSP253240502 | E24: 260000 | F24: 000FXSP253240502 | G24: 0 | H24: INT DR
B25: 8 | C25: 20-Nov-2025 | D25: FX PURCHASE USD,GHS @ 11.05 | E25: 5000000 | F25: 000FXSP253240001 | G25: 0 | H25: INT DR
D27: TOTAL: | E27: =SUM($E$18:$E$26) -> 5290679.6
D30: ADD: DEBIT ORIGINATED BY UBA BUT NOT CREDITED IN OUR BOOKS
B31: 1 | C31: 13-Nov-2025 | D31: 50010010004763 NY11 WIRE OUT FEE-OMN WIRE OUT FEE-OMNAP20254285 | E31: 35 | F31: OMNAP20254285 | G31: 7 | H31: EXT DR
B32: 2 | C32: 13-Nov-2025 | D32: 50010010004763 NY98 WIRE OUT FEE-OMN WIRE OUT FEE-OMNAP20254305 | E32: 35 | F32: OMNAP20254305 | G32: 7 | H32: EXT DR
B33: 3 | C33: 13-Nov-2025 | D33: 50010010004763 NY123 WIRE OUT FEE-OMN WIRE OUT FEE-OMNAP20254310 | E33: 35 | F33: OMNAP20254310 | G33: 7 | H33: EXT DR
B34: 4 | C34: 13-Nov-2025 | D34: 50010010004763 NY57 WIRE OUT FEE-OMN WIRE OUT FEE-OMNAP20254321 | E34: 35 | F34: OMNAP20254321 | G34: 7 | H34: EXT DR
B35: 5 | C35: 13-Nov-2025 | D35: 50010010004763 NY115 WIRE OUT FEE-OMN WIRE OUT FEE-OMNAP20254330 | E35: 35 | F35: OMNAP20254330 | G35: 7 | H35: EXT DR
B36: 6 | C36: 13-Nov-2025 | D36: 50010010004763 NY38 WIRE OUT FEE-OMN WIRE OUT FEE-OMNAP20254333 | E36: 35 | F36: OMNAP20254333 | G36: 7 | H36: EXT DR
B37: 7 | C37: 13-Nov-2025 | D37: 50010010004763 NY108 WIRE OUT FEE-OMN WIRE OUT FEE-OMNAP20254346 | E37: 35 | F37: OMNAP20254346 | G37: 7 | H37: EXT DR
B38: 8 | C38: 13-Nov-2025 | D38: 50010010004763 NY109 WIRE OUT FEE-OMN WIRE OUT FEE-OMNAP20254349 | E38: 35 | F38: OMNAP20254349 | G38: 7 | H38: EXT DR
B39: 9 | C39: 13-Nov-2025 | D39: 50010010004763 NY83 WIRE OUT FEE-OMN WIRE OUT FEE-OMNOPA20251050 | E39: 35 | F39: OMNOPA20251050 | G39: 7 | H39: EXT DR
B40: 10 | C40: 13-Nov-2025 | D40: 50010010004763 NY107 WIRE OUT FEE-OMN WIRE OUT FEE-OMNOPA20251051 | E40: 35 | F40: OMNOPA20251051 | G40: 7 | H40: EXT DR
B41: 11 | C41: 13-Nov-2025 | D41: 50010010004763 NY74 WIRE OUT FEE-OMN WIRE OUT FEE-OMNOPA20251055 | E41: 35 | F41: OMNOPA20251055 | G41: 7 | H41: EXT DR
B42: 12 | C42: 13-Nov-2025 | D42: 50010010004763 NY75 WIRE OUT FEE-OMN WIRE OUT FEE-OMNOPA20251056 | E42: 35 | F42: OMNOPA20251056 | G42: 7 | H42: EXT DR
... B204: 174 | C204: 20-Nov-2025 | D204: 50010010004763 NY66 GUARANTY TRUST B GUARANTY TRUST BANK (GHANA) LTD-000MMOL25323005 | E204: 5500000 | F204: 000MMOL25323005 | G204: 0 | H204: EXT DR
D206: TOTAL: | E206: =SUM($E$31:$E$205) -> 6546021.5
D209: LESS: CREDIT ORIGINATED BY UBA BUT NOT DEBITED IN OUR BOOKS
B210: 1 | C210: 07-Nov-2025 | D210: Fund trf from KLUTSE FELIX DELA_x0002_20251107000024 | E210: 260 | F210: Fund trf from KLUTSE FELIX DELA_x0002_20251107000024 | G210: 13 | H210: EXT CR
B211: 2 | C211: 10-Nov-2025 | D211: Fund trf from BARCLAYS BANK PLC-SWF035776310 | E211: 3985 | F211: SWF035776310 | G211: 10 | H211: EXT CR
B212: 3 | C212: 13-Nov-2025 | D212: 50010010004763 NY231 MUSIC STYLING.CO MUSIC STYLING.COM LIMITED-202511130000050 | E212: 1350 | F212: 50010010004763 NY231 MUSIC STYLING.CO MUSIC STYLING.COM LIMITED-202511130000050 | G212: 7 | H212: EXT CR
B213: 4 | C213: 14-Nov-2025 | D213: 50010010004763 NY154 ZEBLGHAC-512151 ZEBLGHAC-512151 | E213: 310000 | F213: 50010010004763 NY154 ZEBLGHAC-512151 ZEBLGHAC-512151 | G213: 6 | H213: EXT CR
B214: 5 | C214: 17-Nov-2025 | D214: 50010010004763 NY328 GUANGZHOU CARDO GUANGZHOU CARDO AUTO PARTS CO.,LT-202510150000180 | E214: 29965 | F214: 50010010004763 NY328 GUANGZHOU CARDO GUANGZHOU CARDO AUTO PARTS CO.,LT-202510150000180 | G214: 3 | H214: EXT CR
B215: 6 | C215: 19-Nov-2025 | D215: 50010010004763 NY112 TRAVELSCAPE, LLC TRAVELSCAPE, LLC-NOTPROVIDED | E215: 798.85 | F215: 50010010004763 NY112 TRAVELSCAPE, LLC TRAVELSCAPE, LLC-NOTPROVIDED | G215: 1 | H215: EXT CR
B216: 7 | C216: 19-Nov-2025 | D216: 50010010004763 NY111 TRAVELSCAPE, LLC TRAVELSCAPE, LLC-NOTPROVIDED | E216: 1569.2 | F216: 50010010004763 NY111 TRAVELSCAPE, LLC TRAVELSCAPE, LLC-NOTPROVIDED | G216: 1 | H216: EXT CR
B217: 8 | C217: 19-Nov-2025 | D217: 50010010004763 NY197 MALICK ISSAH-INT MALICK ISSAH-INT-00262486 | E217: 4977 | F217: 50010010004763 NY197 MALICK ISSAH-INT MALICK ISSAH-INT-00262486 | G217: 1 | H217: EXT CR
B218: 9 | C218: 19-Nov-2025 | D218: 50010010004763 NY84 1/AFRICAN DEVELO 1/AFRICAN DEVELOPMENT BANK, ABIDJ-202511190000077 | E218: 98990 | F218: 50010010004763 NY84 1/AFRICAN DEVELO 1/AFRICAN DEVELOPMENT BANK, ABIDJ-202511190000077 | G218: 1 | H218: EXT CR
B219: 10 | C219: 20-Nov-2025 | D219: 50010010004763 NY145 DITTO LTD-NOTPRO DITTO LTD-NOTPROVIDED | E219: 420 | F219: NOTPROVIDED | G219: 0 | H219: EXT CR
B220: 11 | C220: 20-Nov-2025 | D220: 50010010004763 NY94 GCB BANK PLC-593 GCB BANK PLC-593235 | E220: 6805.56 | F220: 593235 | G220: 0 | H220: EXT CR
B221: 12 | C221: 20-Nov-2025 | D221: 50010010004763 NY171 ABSA BANK OF GHA ABSA BANK OF GHANA LIMITED-FAS1397749305 | E221: 260000 | F221: FAS1397749305 | G221: 0 | H221: EXT CR
... B223: 14 | C223: 20-Nov-2025 | D223: 50010010004763 NY185 BANK OF GHANA-BA BANK OF GHANA-BATHAC1105OMBLAC | E223: 5000000 | F223: BATHAC1105OMBLAC | G223: 0 | H223: EXT CR
D225: TOTAL: | E225: =SUM($E$210:$E$224) -> 6379106.6
D228: LESS: CREDIT IN OUR BOOKS BUT NOT DEBITED BY UBA
B229: 1 | C229: 05-Nov-2025 | D229: OMNAP20254170 ; TRF IFO CHANGZHOU WENJIAN MACHINERY CO. LTD | E229: 200000 | F229: OMNAP20254170 | G229: 15 | H229: INT CR
B230: 2 | C230: 05-Nov-2025 | D230: OMNAP20254168 ; TRF IFO FUZHOU DONGZAN IMPORT & EXPORT | E230: 200000 | F230: OMNAP20254168 | G230: 15 | H230: INT CR
B231: 3 | C231: 06-Nov-2025 | D231: OMNAP20254228;TRF IFO FUZHOU DONGZAN IMPORT AND EXPORT CO LTD | E231: 200000 | F231: OMNAP20254228 | G231: 14 | H231: INT CR
B232: 4 | C232: 11-Nov-2025 | D232: OMBS/IDC2025135; BILLS FOR COLLECTION IFO AGROFORTUNE INDUSTRIAL CO LTD | E232: 618067 | F232: OMBS/IDC2025135; BILLS FOR COLLECTION IFO AGROFORTUNE INDUSTRIAL CO LTD | G232: 9 | H232: INT CR
B233: 5 | C233: 12-Nov-2025 | D233: 2531601463448000_PYMNT IRO ACCOMODATION AND PER DIEM FOR OFFSHORE TRAINING - MICHAEL AWORTWE | E233: 4400 | F233: 2531601463448000_PYMNT IRO ACCOMODATION AND PER DIEM FOR OFFSHORE TRAINING - MICHAEL AWORTWE | G233: 8 | H233: INT CR
B234: 6 | C234: 14-Nov-2025 | D234: OMNTR20251812 ; TRF IFO PARK YOUNG HEE | E234: 10000 | F234: OMNTR20251812 | G234: 6 | H234: INT CR
B235: 7 | C235: 14-Nov-2025 | D235: FXSWI01141125ZEN FX SWITCH PURCHASE @ 10.99 ZENITH - LAURIUS | E235: 310000 | F235: FXSWI01141125ZEN FX SWITCH PURCHASE @ 10.99 ZENITH - LAURIUS | G235: 6 | H235: INT CR
B236: 8 | C236: 17-Nov-2025 | D236: TRANSFER | E236: 1 | F236: TRANSFER | G236: 3 | H236: INT CR
B237: 9 | C237: 17-Nov-2025 | D237: OMNTR20251826 TRF IFO CHIOMA JENNIFER EGBOCHUKWU | E237: 10000 | F237: OMNTR20251826 | G237: 3 | H237: INT CR
B238: 10 | C238: 17-Nov-2025 | D238: OMNAP20254392 TRF IFO FUZHOU YI MEI TAI TRADING COMPANY | E238: 50000 | F238: OMNAP20254392 | G238: 3 | H238: INT CR
B239: 11 | C239: 18-Nov-2025 | D239: OMNTR20251832 TRF IFO PROJECT RESOURCES SERVICES | E239: 6211.34 | F239: OMNTR20251832 | G239: 2 | H239: INT CR
B240: 12 | C240: 18-Nov-2025 | D240: OMNAP20254426 TRF IFO SAMS CLUB | E240: 50000 | F240: OMNAP20254426 | G240: 2 | H240: INT CR
... B307: 79 | C307: 20-Nov-2025 | D307: OMNOPA20251093; TRF IFO FUELTRADE LIMITED | E307: 643858.84 | F307: OMNOPA20251093 | G307: 0 | H307: INT CR
D309: TOTAL: | E309: =SUM($E$229:$E$308) -> 5937616.3
D312: GRAND TOTAL | E312: =ABS(E13+$E$27-$E$309+$E$206-$E$225) -> 21846264
D313: INTERNAL ACCOUNT BALANCE AS AT Nov 20, 2025 | E313: 21846264 | I313: DR
D314: DIFFERENCE | E314: =$E$313-$E$312 -> 0
D316: PREPARED BY: | E316: kenneth nuamah | F316: DATE: | G316: 45981
D319: REVIEWED BY: | F319: DATE:

Sheet ZENITH CEDI
A1: Field_1 | B1: Field_2 | C1: Field_3 | D1: Field_4 | E1: Field_5 | F1: Field_6 | G1: Field_7 | H1: Field_8 | I1: FIELD_9
B4: DEPT | D4: OPERATIONS | E4: BANK ACCOUNT NUMBER | F4: ^6010158915
B6: BRANCH | D6: HEAD OFFICE | E6: GENERAL LEDGER NAME | F6: ZENITH BANK CEDI
B8: REPORTING DATE | D8: 20-Nov-25 | E8: GENERAL LEDGER NUMBER | F8: 0010000140018
B10: REPORTING UNIT | D10: RECONCILIATION
C13: 20-Nov-25 | D13: BALANCE PER BANK STATEMENT | E13: 2846163.3 | I13: CR
B15: SN | C15: DATE | D15: DESCRIPTION | E15: AMOUNT | F15: GL Ref No. | G15: AGING(DAYS) | H15: RECON
D17: ADD: DEBIT IN OUR BOOKS BUT NOT CREDITED BY ZENITH
D20: TOTAL: | E20: =SUM($E$18:$E$19) -> 0
D23: ADD: DEBIT ORIGINATED BY ZENITH BUT NOT CREDITED IN OUR BOOKS
D26: TOTAL: | E26: =SUM($E$24:$E$25) -> 0
D29: LESS: CREDIT ORIGINATED BY ZENITH BUT NOT DEBITED IN OUR BOOKS
B30: 1 | C30: 20-Nov-2025 | D30: 19 NOVEMBER 2025/MG GHS | E30: 10891.91 | G30: 0 | H30: EXT CR
D32: TOTAL: | E32: =SUM($E$30:$E$31) -> 10891.91
D35: LESS: CREDIT IN OUR BOOKS BUT NOT DEBITED BY ZENITH
D38: TOTAL: | E38: =SUM($E$36:$E$37) -> 0
D41: GRAND TOTAL | E41: =ABS(E13+$E$20-$E$38+$E$26-$E$32) -> 2835271.4
D42: INTERNAL ACCOUNT BALANCE AS AT Nov 20, 2025 | E42: 2835271.4 | I42: DR
D43: DIFFERENCE | E43: =$E$42-$E$41 -> 0
D45: PREPARED BY: | E45: kenneth nuamah | F45: DATE: | G45: 45981
D48: REVIEWED BY: | F48: DATE:

Sheet ZENITH OPS
A1: Field_1 | B1: Field_2 | C1: Field_3 | D1: Field_4 | E1: Field_5 | F1: Field_6 | G1: Field_7 | H1: Field_8 | I1: FIELD_9
B4: DEPT | D4: OPERATIONS | E4: BANK ACCOUNT NUMBER | F4: ^CA6010120705/CD1060101229/6010503159
B6: BRANCH | D6: HEAD OFFICE | E6: GENERAL LEDGER NAME | F6: ZENITH BANK OPS CEDI
B8: REPORTING DATE | D8: 20-Nov-25 | E8: GENERAL LEDGER NUMBER | F8: 0010000140020
B10: REPORTING UNIT | D10: RECONCILIATION
C13: 20-Nov-25 | D13: BALANCE PER BANK STATEMENT | E13: 462963.52 | I13: CR
B15: SN | C15: DATE | D15: DESCRIPTION | E15: AMOUNT | F15: GL Ref No. | G15: AGING(DAYS) | H15: RECON
D17: ADD: DEBIT IN OUR BOOKS BUT NOT CREDITED BY ZENITH
D20: TOTAL: | E20: =SUM($E$18:$E$19) -> 0
D23: ADD: DEBIT ORIGINATED BY ZENITH BUT NOT CREDITED IN OUR BOOKS
D26: TOTAL: | E26: =SUM($E$24:$E$25) -> 0
D29: LESS: CREDIT ORIGINATED BY ZENITH BUT NOT DEBITED IN OUR BOOKS
D32: TOTAL: | E32: =SUM($E$30:$E$31) -> 0
D35: LESS: CREDIT IN OUR BOOKS BUT NOT DEBITED BY ZENITH
D38: TOTAL: | E38: =SUM($E$36:$E$37) -> 0
D41: GRAND TOTAL | E41: =ABS(E13+$E$20-$E$38+$E$26-$E$32) -> 462963.52
D42: INTERNAL ACCOUNT BALANCE AS AT Nov 20, 2025 | E42: 462963.52 | I42: CR
D43: DIFFERENCE | E43: =$E$42-$E$41 -> 0
D45: PREPARED BY: | E45: kenneth nuamah | F45: DATE: | G45: 45981
D48: REVIEWED BY: | F48: DATE:

Sheet ZENITH USD
A1: Field_1 | B1: Field_2 | C1: Field_3 | D1: Field_4 | E1: Field_5 | F1: Field_6 | G1: Field_7 | H1: Field_8 | I1: FIELD_9
B4: DEPT | D4: OPERATIONS | E4: BANK ACCOUNT NUMBER | F4: 'SA 6040140186
B6: BRANCH | D6: HEAD OFFICE | E6: GENERAL LEDGER NAME | F6: ZENITH BANK USD
B8: REPORTING DATE | D8: 20-Nov-25 | E8: GENERAL LEDGER NUMBER | F8: 0020000140017
B10: REPORTING UNIT | D10: RECONCILIATION
C13: 20-Nov-25 | D13: BALANCE PER BANK STATEMENT | E13: 273426.43 | I13: CR
B15: SN | C15: DATE | D15: DESCRIPTION | E15: AMOUNT | F15: GL Ref No. | G15: AGING(DAYS) | H15: RECON
D17: ADD: DEBIT IN OUR BOOKS BUT NOT CREDITED BY ZENITH
D20: TOTAL: | E20: =SUM($E$18:$E$19) -> 0
D23: ADD: DEBIT ORIGINATED BY ZENITH BUT NOT CREDITED IN OUR BOOKS
D26: TOTAL: | E26: =SUM($E$24:$E$25) -> 0
D29: LESS: CREDIT ORIGINATED BY ZENITH BUT NOT DEBITED IN OUR BOOKS
B30: 1 | C30: 20-Nov-2025 | D30: MG SETT/SUB AGENT USD DUE/19 | E30: 990.18 | G30: 0 | H30: EXT CR
D32: TOTAL: | E32: =SUM($E$30:$E$31) -> 990.18
D35: LESS: CREDIT IN OUR BOOKS BUT NOT DEBITED BY ZENITH
D38: TOTAL: | E38: =SUM($E$36:$E$37) -> 0
D41: GRAND TOTAL | E41: =ABS(E13+$E$20-$E$38+$E$26-$E$32) -> 272436.25
D42: INTERNAL ACCOUNT BALANCE AS AT Nov 20, 2025 | E42: 272436.25 | I42: DR
D43: DIFFERENCE | E43: =$E$42-$E$41 -> 0
D45: PREPARED BY: | E45: kenneth nuamah | F45: DATE: | G45: 45981
D48: REVIEWED BY: | F48: DATE:

Sheet SUMMARY CHECK
A1: Field_1 | B1: Field_2 | C1: Field_3 | D1: Field_4 | E1: Field_5 | F1: Field_6 | G1: Field_7
A3: OmniBSIC Bank Ghana Limited
A4: Bank Reconciliation Summary
A5: DATE | B5: %rDATE%
A7: S/N | B7: NOSTRO/NAME | C7: CCY | D7: GL BALANCE | E7: BANK BALANCE | F7: VARIANCE | G7: STATUS
A8: BOG | B8: BOG GHS | C8: GHS | D8: 0 | E8: 0 | F8: =IF(ISERROR(D8+E8),0,D8+E8) -> 0
A9: BOG | B9: BOG USD | C9: USD | D9: 0 | E9: 0 | F9: =IF(ISERROR(D9+E9),0,D9+E9) -> 0
A10: BOG | B10: BOG EUR | C10: EUR | D10: 0 | E10: 0 | F10: =IF(ISERROR(D10+E10),0,D10+E10) -> 0
A11: BOG | B11: BOG GBP | C11: GBP | D11: 0 | E11: 0 | F11: =IF(ISERROR(D11+E11),0,D11+E11) -> 0
A12: BOG | B12: BOG PAPSS | C12: GHS | D12: 0 | E12: 0 | F12: =IF(ISERROR(D12+E12),0,D12+E12) -> 0
A14: BOG TAMALE | B14: BOG TLE GHS | C14: GHS | D14: 0 | E14: 0 | F14: =IF(ISERROR(D14+E14),0,D14+E14) -> 0
A15: BOG TAMALE | B15: BOG TLE USD | C15: USD | D15: 0 | E15: 0 | F15: =IF(ISERROR(D15+E15),0,D15+E15) -> 0
A16: BOG TAMALE | B16: BOG TLE EUR | C16: EUR | D16: 0 | E16: 0 | F16: =IF(ISERROR(D16+E16),0,D16+E16) -> 0
A18: BOG SUNYANI | B18: BOG SYI GHS | C18: GHS | D18: 0 | E18: 0 | F18: =IF(ISERROR(D18+E18),0,D18+E18) -> 0
A19: BOG SUNYANI | B19: BOG SYI USD | C19: USD | D19: 0 | E19: 0 | F19: =IF(ISERROR(D19+E19),0,D19+E19) -> 0
A21: BOG KUMASI | B21: BOG KSI GHS | C21: GHS | D21: 0 | E21: 0 | F21: =IF(ISERROR(D21+E21),0,D21+E21) -> 0
A22: BOG KUMASI | B22: BOG KSI USD | C22: USD | D22: 0 | E22: 0 | F22: =IF(ISERROR(D22+E22),0,D22+E22) -> 0
... A71: TG | B71: TOGO XOF | C71: XOF | D71: 0 | E71: 0 | F71: =IF(ISERROR(D71+E71),0,D71+E71) -> 0
C73: TOTAL | D73: =IF(ISERROR(SUM(D8:D71)),0,SUM(D8:D71)) -> 0 | E73: =IF(ISERROR(SUM(E8:E71)),0,SUM(E8:E71)) -> 0 | F73: =IF(ISERROR(D73+E73),0,D73+E73) -> 0
A76: CONSOLIDATED CHECK
A78: S/N | B78: DESCRIPTION | D78: G/L BALANCES | E78: B/S BALANCES | F78: VARIANCE | G78: VARIANCE (GHS EQUIVALENT)
A79: 1 | B79: GHS | D79: 0 | E79: 0 | F79: =IF(ISERROR(D79+E79),0,D79+E79) -> 0 | G79: =IFERROR(F79*VLOOKUP($B79,'BOG DAILY RATES'!$A:$C,3,FALSE),0) -> 0
A80: 2 | B80: USD | D80: 0 | E80: 0 | F80: =IF(ISERROR(D80+E80),0,D80+E80) -> 0 | G80: =IFERROR(F80*VLOOKUP($B80,'BOG DAILY RATES'!$A:$C,3,FALSE),0) -> 0
A81: 3 | B81: EUR | D81: 0 | E81: 0 | F81: =IF(ISERROR(D81+E81),0,D81+E81) -> 0 | G81: =IFERROR(F81*VLOOKUP($B81,'BOG DAILY RATES'!$A:$C,3,FALSE),0) -> 0
A82: 4 | B82: GBP | D82: 0 | E82: 0 | F82: =IF(ISERROR(D82+E82),0,D82+E82) -> 0 | G82: =IFERROR(F82*VLOOKUP($B82,'BOG DAILY RATES'!$A:$C,3,FALSE),0) -> 0
A83: 5 | B83: XOF | D83: 0 | E83: 0 | F83: =IF(ISERROR(D83+E83),0,D83+E83) -> 0 | G83: =IFERROR(F83*VLOOKUP($B83,'BOG DAILY RATES'!$A:$C,3,FALSE),0) -> 0
C85: TOTAL | D85: =IF(ISERROR(SUM(D79:D83)),0,SUM(D79:D83)) -> 0 | E85: =IF(ISERROR(SUM(E79:E83)),0,SUM(E79:E83)) -> 0 | F85: =IF(ISERROR(D85+E85),0,D85+E85) -> 0 | G85: =IF(ISERROR(SUM(G79:G83)),0,SUM(G79:G83)) -> 0

Sheet BOG DAILY RATES
A1: Field_1 | B1: Field_2 | C1: Field_3
A3: Currency | B3: Rate On Portal | C3: Rate Applied
A4: GHS | B4: 1 | C4: 1
A5: USD | C5: =IF(ISERROR(B5),0,SUM(B5)) -> 0
A6: EUR | C6: =IF(ISERROR(B6),0,SUM(B6)) -> 0
A7: GBP | C7: =IF(ISERROR(B7),0,SUM(B7)) -> 0
A8: XOF | C8: =IF(ISERROR(1/B8),0,SUM(1/B8)) -> 0
